{
"meta":{"test_sets":[],"test_metrics":[],"learn_metrics":[{"best_value":"Min","name":"MultiClass"}],"launch_mode":"Train","parameters":"","iteration_count":1000,"learn_sets":["learn"],"name":"experiment"},
"iterations":[
{"learn":[1.846836402],"iteration":0,"passed_time":0.01552319222,"remaining_time":15.50766903},
{"learn":[1.767104684],"iteration":1,"passed_time":0.02097218029,"remaining_time":10.46511796},
{"learn":[1.702067073],"iteration":2,"passed_time":0.02633111507,"remaining_time":8.750707242},
{"learn":[1.652400559],"iteration":3,"passed_time":0.03191224048,"remaining_time":7.94614788},
{"learn":[1.605971287],"iteration":4,"passed_time":0.03705100292,"remaining_time":7.37314958},
{"learn":[1.567364202],"iteration":5,"passed_time":0.04213333197,"remaining_time":6.980088664},
{"learn":[1.535336413],"iteration":6,"passed_time":0.04714404014,"remaining_time":6.687718836},
{"learn":[1.507298819],"iteration":7,"passed_time":0.05197222052,"remaining_time":6.444555345},
{"learn":[1.480837932],"iteration":8,"passed_time":0.05685347892,"remaining_time":6.260199734},
{"learn":[1.460468681],"iteration":9,"passed_time":0.0621444298,"remaining_time":6.15229855},
{"learn":[1.443090501],"iteration":10,"passed_time":0.06731647397,"remaining_time":6.052362978},
{"learn":[1.427044456],"iteration":11,"passed_time":0.07217790447,"remaining_time":5.942647468},
{"learn":[1.41343466],"iteration":12,"passed_time":0.07759564285,"remaining_time":5.891299961},
{"learn":[1.399591104],"iteration":13,"passed_time":0.08307364507,"remaining_time":5.850758146},
{"learn":[1.384708669],"iteration":14,"passed_time":0.08903360466,"remaining_time":5.846540039},
{"learn":[1.373411601],"iteration":15,"passed_time":0.09181369574,"remaining_time":5.646542288},
{"learn":[1.362252603],"iteration":16,"passed_time":0.09785164804,"remaining_time":5.658127649},
{"learn":[1.353560602],"iteration":17,"passed_time":0.10382789,"remaining_time":5.664388224},
{"learn":[1.343834547],"iteration":18,"passed_time":0.109643321,"remaining_time":5.661057783},
{"learn":[1.335361885],"iteration":19,"passed_time":0.1154466817,"remaining_time":5.656887402},
{"learn":[1.327115073],"iteration":20,"passed_time":0.1209125701,"remaining_time":5.636828863},
{"learn":[1.323355946],"iteration":21,"passed_time":0.1264167932,"remaining_time":5.619801081},
{"learn":[1.318541391],"iteration":22,"passed_time":0.1318649234,"remaining_time":5.601392615},
{"learn":[1.312800959],"iteration":23,"passed_time":0.1383790595,"remaining_time":5.627415086},
{"learn":[1.308870673],"iteration":24,"passed_time":0.144384918,"remaining_time":5.6310118},
{"learn":[1.304795383],"iteration":25,"passed_time":0.1501000249,"remaining_time":5.622977855},
{"learn":[1.300328174],"iteration":26,"passed_time":0.1557178119,"remaining_time":5.611608556},
{"learn":[1.295961536],"iteration":27,"passed_time":0.1615200692,"remaining_time":5.60705383},
{"learn":[1.29220663],"iteration":28,"passed_time":0.1670094061,"remaining_time":5.591935633},
{"learn":[1.28814094],"iteration":29,"passed_time":0.1728058972,"remaining_time":5.587390677},
{"learn":[1.285499357],"iteration":30,"passed_time":0.178113446,"remaining_time":5.567481586},
{"learn":[1.281578556],"iteration":31,"passed_time":0.18366069,"remaining_time":5.555735871},
{"learn":[1.278447748],"iteration":32,"passed_time":0.1891850922,"remaining_time":5.543696489},
{"learn":[1.274945108],"iteration":33,"passed_time":0.1947330969,"remaining_time":5.532710931},
{"learn":[1.272517537],"iteration":34,"passed_time":0.2002331637,"remaining_time":5.520714371},
{"learn":[1.270844113],"iteration":35,"passed_time":0.2062390732,"remaining_time":5.52262407},
{"learn":[1.268690019],"iteration":36,"passed_time":0.2116745088,"remaining_time":5.509258161},
{"learn":[1.265447021],"iteration":37,"passed_time":0.2173879248,"remaining_time":5.503346939},
{"learn":[1.262329312],"iteration":38,"passed_time":0.2232722054,"remaining_time":5.501656138},
{"learn":[1.260089409],"iteration":39,"passed_time":0.2291165467,"remaining_time":5.49879712},
{"learn":[1.257814033],"iteration":40,"passed_time":0.2350368534,"remaining_time":5.497569328},
{"learn":[1.254272924],"iteration":41,"passed_time":0.2405051917,"remaining_time":5.485808897},
{"learn":[1.251699358],"iteration":42,"passed_time":0.2459774445,"remaining_time":5.474428242},
{"learn":[1.2490935],"iteration":43,"passed_time":0.2517554999,"remaining_time":5.469960406},
{"learn":[1.246200861],"iteration":44,"passed_time":0.2573895374,"remaining_time":5.462377959},
{"learn":[1.243612137],"iteration":45,"passed_time":0.2631915442,"remaining_time":5.458363765},
{"learn":[1.24150983],"iteration":46,"passed_time":0.2687359804,"remaining_time":5.449050837},
{"learn":[1.239451743],"iteration":47,"passed_time":0.2752486053,"remaining_time":5.459097339},
{"learn":[1.237088217],"iteration":48,"passed_time":0.2813580331,"remaining_time":5.460642641},
{"learn":[1.234988048],"iteration":49,"passed_time":0.2868385614,"remaining_time":5.449932666},
{"learn":[1.232990179],"iteration":50,"passed_time":0.2928721185,"remaining_time":5.44971844},
{"learn":[1.230462152],"iteration":51,"passed_time":0.2985975021,"remaining_time":5.443662153},
{"learn":[1.228743739],"iteration":52,"passed_time":0.3045984638,"remaining_time":5.442542363},
{"learn":[1.22761068],"iteration":53,"passed_time":0.31040132,"remaining_time":5.437771273},
{"learn":[1.225935494],"iteration":54,"passed_time":0.3160251724,"remaining_time":5.429887053},
{"learn":[1.224080916],"iteration":55,"passed_time":0.3218852845,"remaining_time":5.426066225},
{"learn":[1.222496931],"iteration":56,"passed_time":0.3277238105,"remaining_time":5.421816725},
{"learn":[1.220708854],"iteration":57,"passed_time":0.3332141494,"remaining_time":5.411857392},
{"learn":[1.218358584],"iteration":58,"passed_time":0.339080739,"remaining_time":5.408050431},
{"learn":[1.216766277],"iteration":59,"passed_time":0.3448188949,"remaining_time":5.402162687},
{"learn":[1.215025967],"iteration":60,"passed_time":0.3508817303,"remaining_time":5.401277782},
{"learn":[1.213638089],"iteration":61,"passed_time":0.3570778913,"remaining_time":5.402242936},
{"learn":[1.211956503],"iteration":62,"passed_time":0.3630316911,"remaining_time":5.399376104},
{"learn":[1.210330642],"iteration":63,"passed_time":0.3687243157,"remaining_time":5.392593117},
{"learn":[1.209158514],"iteration":64,"passed_time":0.3743314864,"remaining_time":5.384614458},
{"learn":[1.207819202],"iteration":65,"passed_time":0.3792779887,"remaining_time":5.367358203},
{"learn":[1.207024905],"iteration":66,"passed_time":0.3843436287,"remaining_time":5.352128441},
{"learn":[1.205327901],"iteration":67,"passed_time":0.3901905221,"remaining_time":5.347905391},
{"learn":[1.203741737],"iteration":68,"passed_time":0.3960546935,"remaining_time":5.343868401},
{"learn":[1.202429242],"iteration":69,"passed_time":0.4016577406,"remaining_time":5.336309982},
{"learn":[1.20098517],"iteration":70,"passed_time":0.4071646044,"remaining_time":5.327548134},
{"learn":[1.199629009],"iteration":71,"passed_time":0.4130355822,"remaining_time":5.323569726},
{"learn":[1.198147003],"iteration":72,"passed_time":0.4188941489,"remaining_time":5.319381864},
{"learn":[1.19700058],"iteration":73,"passed_time":0.4250512922,"remaining_time":5.318885088},
{"learn":[1.196044201],"iteration":74,"passed_time":0.4309854948,"remaining_time":5.315487769},
{"learn":[1.194753289],"iteration":75,"passed_time":0.4368009581,"remaining_time":5.310580069},
{"learn":[1.192613684],"iteration":76,"passed_time":0.442857784,"remaining_time":5.308542008},
{"learn":[1.191405107],"iteration":77,"passed_time":0.4485760167,"remaining_time":5.302398557},
{"learn":[1.190023752],"iteration":78,"passed_time":0.4541458911,"remaining_time":5.294536275},
{"learn":[1.188137779],"iteration":79,"passed_time":0.4598490368,"remaining_time":5.288263923},
{"learn":[1.186822012],"iteration":80,"passed_time":0.4654994437,"remaining_time":5.281407269},
{"learn":[1.184555367],"iteration":81,"passed_time":0.4712595247,"remaining_time":5.275807849},
{"learn":[1.183125674],"iteration":82,"passed_time":0.4773826845,"remaining_time":5.274215924},
{"learn":[1.182170366],"iteration":83,"passed_time":0.4828779993,"remaining_time":5.265669612},
{"learn":[1.181003132],"iteration":84,"passed_time":0.4886558657,"remaining_time":5.260236672},
{"learn":[1.179550601],"iteration":85,"passed_time":0.4940523531,"remaining_time":5.250742451},
{"learn":[1.178457432],"iteration":86,"passed_time":0.4997970601,"remaining_time":5.244996735},
{"learn":[1.177197745],"iteration":87,"passed_time":0.5060442571,"remaining_time":5.244458664},
{"learn":[1.17601393],"iteration":88,"passed_time":0.5119024975,"remaining_time":5.239810958},
{"learn":[1.174310507],"iteration":89,"passed_time":0.5175430195,"remaining_time":5.232934975},
{"learn":[1.173415347],"iteration":90,"passed_time":0.5229162899,"remaining_time":5.223416566},
{"learn":[1.17198593],"iteration":91,"passed_time":0.5286375752,"remaining_time":5.217423024},
{"learn":[1.171298372],"iteration":92,"passed_time":0.5341625176,"remaining_time":5.209520467},
{"learn":[1.170068452],"iteration":93,"passed_time":0.5398971016,"remaining_time":5.203689085},
{"learn":[1.168991809],"iteration":94,"passed_time":0.5456876356,"remaining_time":5.19839274},
{"learn":[1.16786997],"iteration":95,"passed_time":0.5513594397,"remaining_time":5.191968057},
{"learn":[1.166602566],"iteration":96,"passed_time":0.5574287303,"remaining_time":5.189259211},
{"learn":[1.165399255],"iteration":97,"passed_time":0.5630576445,"remaining_time":5.182428524},
{"learn":[1.164173488],"iteration":98,"passed_time":0.5688033991,"remaining_time":5.176685481},
{"learn":[1.163291844],"iteration":99,"passed_time":0.5745084076,"remaining_time":5.170575668},
{"learn":[1.162169375],"iteration":100,"passed_time":0.5803662708,"remaining_time":5.16583443},
{"learn":[1.161012373],"iteration":101,"passed_time":0.5864321699,"remaining_time":5.162902829},
{"learn":[1.15933813],"iteration":102,"passed_time":0.5921835489,"remaining_time":5.157171295},
{"learn":[1.158521793],"iteration":103,"passed_time":0.5981870238,"remaining_time":5.153611282},
{"learn":[1.156993491],"iteration":104,"passed_time":0.6036643102,"remaining_time":5.145519597},
{"learn":[1.155631217],"iteration":105,"passed_time":0.60956233,"remaining_time":5.141025688},
{"learn":[1.154478056],"iteration":106,"passed_time":0.6150844099,"remaining_time":5.133368019},
{"learn":[1.152824641],"iteration":107,"passed_time":0.6207033667,"remaining_time":5.126550029},
{"learn":[1.150445391],"iteration":108,"passed_time":0.6265796173,"remaining_time":5.121857238},
{"learn":[1.149341738],"iteration":109,"passed_time":0.6322440328,"remaining_time":5.115428992},
{"learn":[1.148415905],"iteration":110,"passed_time":0.6379824904,"remaining_time":5.109607513},
{"learn":[1.147350612],"iteration":111,"passed_time":0.6438219361,"remaining_time":5.104588207},
{"learn":[1.146454858],"iteration":112,"passed_time":0.649597148,"remaining_time":5.099050179},
{"learn":[1.145301141],"iteration":113,"passed_time":0.6553597304,"remaining_time":5.093409835},
{"learn":[1.143867252],"iteration":114,"passed_time":0.6612410236,"remaining_time":5.08868092},
{"learn":[1.143038379],"iteration":115,"passed_time":0.6668210693,"remaining_time":5.081636425},
{"learn":[1.14185316],"iteration":116,"passed_time":0.6727721076,"remaining_time":5.077416846},
{"learn":[1.140901663],"iteration":117,"passed_time":0.6787235666,"remaining_time":5.073171065},
{"learn":[1.140340012],"iteration":118,"passed_time":0.6842994935,"remaining_time":5.066116419},
{"learn":[1.139067871],"iteration":119,"passed_time":0.6898290291,"remaining_time":5.058746213},
{"learn":[1.137902892],"iteration":120,"passed_time":0.695302959,"remaining_time":5.051002487},
{"learn":[1.136908422],"iteration":121,"passed_time":0.7009070709,"remaining_time":5.044232854},
{"learn":[1.136163169],"iteration":122,"passed_time":0.7065235015,"remaining_time":5.037570007},
{"learn":[1.135024626],"iteration":123,"passed_time":0.7120308549,"remaining_time":5.030153459},
{"learn":[1.133982216],"iteration":124,"passed_time":0.7175388505,"remaining_time":5.022771953},
{"learn":[1.133230125],"iteration":125,"passed_time":0.723335826,"remaining_time":5.017424698},
{"learn":[1.132289999],"iteration":126,"passed_time":0.7287147877,"remaining_time":5.009196926},
{"learn":[1.130860909],"iteration":127,"passed_time":0.7341379842,"remaining_time":5.001315017},
{"learn":[1.129557499],"iteration":128,"passed_time":0.7399201408,"remaining_time":4.995894904},
{"learn":[1.128720446],"iteration":129,"passed_time":0.7453988313,"remaining_time":4.988438332},
{"learn":[1.127920256],"iteration":130,"passed_time":0.7515781299,"remaining_time":4.985659503},
{"learn":[1.126834727],"iteration":131,"passed_time":0.7575729765,"remaining_time":4.981616239},
{"learn":[1.126309358],"iteration":132,"passed_time":0.7630383259,"remaining_time":4.974091944},
{"learn":[1.12518973],"iteration":133,"passed_time":0.7686527338,"remaining_time":4.967561697},
{"learn":[1.124457903],"iteration":134,"passed_time":0.7743908774,"remaining_time":4.961837844},
{"learn":[1.12323755],"iteration":135,"passed_time":0.7804804813,"remaining_time":4.958346587},
{"learn":[1.122255973],"iteration":136,"passed_time":0.7864337651,"remaining_time":4.953958681},
{"learn":[1.121254517],"iteration":137,"passed_time":0.7918988369,"remaining_time":4.946498532},
{"learn":[1.120553898],"iteration":138,"passed_time":0.7973552746,"remaining_time":4.939013607},
{"learn":[1.119419196],"iteration":139,"passed_time":0.803005433,"remaining_time":4.93274766},
{"learn":[1.118178522],"iteration":140,"passed_time":0.8088431611,"remaining_time":4.927633159},
{"learn":[1.117197943],"iteration":141,"passed_time":0.8146968776,"remaining_time":4.922605077},
{"learn":[1.11634615],"iteration":142,"passed_time":0.82035968,"remaining_time":4.916421299},
{"learn":[1.115698716],"iteration":143,"passed_time":0.8260032809,"remaining_time":4.910130614},
{"learn":[1.114551052],"iteration":144,"passed_time":0.8316420552,"remaining_time":4.903820394},
{"learn":[1.11345694],"iteration":145,"passed_time":0.8377089118,"remaining_time":4.900023361},
{"learn":[1.112499741],"iteration":146,"passed_time":0.8429507621,"remaining_time":4.891408164},
{"learn":[1.111827723],"iteration":147,"passed_time":0.8491762572,"remaining_time":4.888501156},
{"learn":[1.110743541],"iteration":148,"passed_time":0.8553015153,"remaining_time":4.884977111},
{"learn":[1.109929839],"iteration":149,"passed_time":0.8608494517,"remaining_time":4.878146893},
{"learn":[1.108556684],"iteration":150,"passed_time":0.8663837559,"remaining_time":4.871257012},
{"learn":[1.107735753],"iteration":151,"passed_time":0.8719214174,"remaining_time":4.864403697},
{"learn":[1.106850943],"iteration":152,"passed_time":0.8774272901,"remaining_time":4.8573916},
{"learn":[1.10574453],"iteration":153,"passed_time":0.8830469627,"remaining_time":4.851024224},
{"learn":[1.104931393],"iteration":154,"passed_time":0.889048013,"remaining_time":4.846745619},
{"learn":[1.103322418],"iteration":155,"passed_time":0.8944538634,"remaining_time":4.839224748},
{"learn":[1.102316233],"iteration":156,"passed_time":0.9002130767,"remaining_time":4.833628176},
{"learn":[1.101536403],"iteration":157,"passed_time":0.9058260415,"remaining_time":4.827250171},
{"learn":[1.100650973],"iteration":158,"passed_time":0.911690643,"remaining_time":4.822212772},
{"learn":[1.100091897],"iteration":159,"passed_time":0.9171553636,"remaining_time":4.815065659},
{"learn":[1.099103875],"iteration":160,"passed_time":0.9228662305,"remaining_time":4.809222158},
{"learn":[1.098175479],"iteration":161,"passed_time":0.9287369936,"remaining_time":4.804207411},
{"learn":[1.097222387],"iteration":162,"passed_time":0.9350660267,"remaining_time":4.801535364},
{"learn":[1.096180483],"iteration":163,"passed_time":0.940904975,"remaining_time":4.796320482},
{"learn":[1.094929942],"iteration":164,"passed_time":0.9470462078,"remaining_time":4.792627779},
{"learn":[1.093847046],"iteration":165,"passed_time":0.9532054925,"remaining_time":4.78899627},
{"learn":[1.092651813],"iteration":166,"passed_time":0.9593827646,"remaining_time":4.785424209},
{"learn":[1.0922591],"iteration":167,"passed_time":0.9650279374,"remaining_time":4.779185976},
{"learn":[1.091129439],"iteration":168,"passed_time":0.9707562534,"remaining_time":4.773363589},
{"learn":[1.089623795],"iteration":169,"passed_time":0.976936187,"remaining_time":4.769747266},
{"learn":[1.088946453],"iteration":170,"passed_time":0.9829620587,"remaining_time":4.765354074},
{"learn":[1.087770076],"iteration":171,"passed_time":0.9888617846,"remaining_time":4.760334637},
{"learn":[1.087058506],"iteration":172,"passed_time":1.011109198,"remaining_time":4.83345264},
{"learn":[1.0860793],"iteration":173,"passed_time":1.01657795,"remaining_time":4.825824063},
{"learn":[1.085454268],"iteration":174,"passed_time":1.022278319,"remaining_time":4.819312077},
{"learn":[1.084427198],"iteration":175,"passed_time":1.027685655,"remaining_time":4.811437385},
{"learn":[1.083836008],"iteration":176,"passed_time":1.03298516,"remaining_time":4.803089191},
{"learn":[1.083147832],"iteration":177,"passed_time":1.038689163,"remaining_time":4.796643215},
{"learn":[1.082414192],"iteration":178,"passed_time":1.044693552,"remaining_time":4.791583274},
{"learn":[1.081557247],"iteration":179,"passed_time":1.050933718,"remaining_time":4.787586938},
{"learn":[1.080834042],"iteration":180,"passed_time":1.056871129,"remaining_time":4.782195884},
{"learn":[1.079949214],"iteration":181,"passed_time":1.063060989,"remaining_time":4.777933456},
{"learn":[1.078540939],"iteration":182,"passed_time":1.068902284,"remaining_time":4.772093802},
{"learn":[1.077715529],"iteration":183,"passed_time":1.074864519,"remaining_time":4.766790477},
{"learn":[1.076727966],"iteration":184,"passed_time":1.080490931,"remaining_time":4.760000588},
{"learn":[1.076090568],"iteration":185,"passed_time":1.086480001,"remaining_time":4.754810329},
{"learn":[1.075096147],"iteration":186,"passed_time":1.092199658,"remaining_time":4.748440224},
{"learn":[1.074002192],"iteration":187,"passed_time":1.098430418,"remaining_time":4.744284573},
{"learn":[1.073420604],"iteration":188,"passed_time":1.105130257,"remaining_time":4.742119781},
{"learn":[1.072541755],"iteration":189,"passed_time":1.111047838,"remaining_time":4.736572361},
{"learn":[1.071315089],"iteration":190,"passed_time":1.117323038,"remaining_time":4.732535798},
{"learn":[1.070310452],"iteration":191,"passed_time":1.123749434,"remaining_time":4.729112202},
{"learn":[1.069322363],"iteration":192,"passed_time":1.129967728,"remaining_time":4.72478734},
{"learn":[1.068417467],"iteration":193,"passed_time":1.135960906,"remaining_time":4.719507682},
{"learn":[1.067154636],"iteration":194,"passed_time":1.14189923,"remaining_time":4.713994259},
{"learn":[1.066357649],"iteration":195,"passed_time":1.147747619,"remaining_time":4.708107582},
{"learn":[1.065129317],"iteration":196,"passed_time":1.15321445,"remaining_time":4.700666005},
{"learn":[1.064090287],"iteration":197,"passed_time":1.158853697,"remaining_time":4.693942754},
{"learn":[1.063015519],"iteration":198,"passed_time":1.164507913,"remaining_time":4.687290644},
{"learn":[1.061809446],"iteration":199,"passed_time":1.170133913,"remaining_time":4.680535652},
{"learn":[1.06093021],"iteration":200,"passed_time":1.175779393,"remaining_time":4.673869327},
{"learn":[1.059711788],"iteration":201,"passed_time":1.181224771,"remaining_time":4.666422611},
{"learn":[1.058857589],"iteration":202,"passed_time":1.186734195,"remaining_time":4.65924706},
{"learn":[1.057700551],"iteration":203,"passed_time":1.192056116,"remaining_time":4.651356218},
{"learn":[1.05702651],"iteration":204,"passed_time":1.198285169,"remaining_time":4.647008339},
{"learn":[1.056119472],"iteration":205,"passed_time":1.203961423,"remaining_time":4.640511503},
{"learn":[1.055310196],"iteration":206,"passed_time":1.209689671,"remaining_time":4.634221783},
{"learn":[1.054421716],"iteration":207,"passed_time":1.215366031,"remaining_time":4.627739887},
{"learn":[1.053510531],"iteration":208,"passed_time":1.221047706,"remaining_time":4.621285815},
{"learn":[1.052688659],"iteration":209,"passed_time":1.226948219,"remaining_time":4.615662346},
{"learn":[1.051707431],"iteration":210,"passed_time":1.232868154,"remaining_time":4.610108879},
{"learn":[1.05090313],"iteration":211,"passed_time":1.238887921,"remaining_time":4.604923028},
{"learn":[1.049657771],"iteration":212,"passed_time":1.245217234,"remaining_time":4.600873066},
{"learn":[1.048863397],"iteration":213,"passed_time":1.251663694,"remaining_time":4.597232074},
{"learn":[1.048026249],"iteration":214,"passed_time":1.257874103,"remaining_time":4.592703121},
{"learn":[1.047363715],"iteration":215,"passed_time":1.263904509,"remaining_time":4.587505254},
{"learn":[1.046571878],"iteration":216,"passed_time":1.270321243,"remaining_time":4.583693701},
{"learn":[1.045039419],"iteration":217,"passed_time":1.276372834,"remaining_time":4.578548424},
{"learn":[1.044415817],"iteration":218,"passed_time":1.281938891,"remaining_time":4.57166335},
{"learn":[1.043667048],"iteration":219,"passed_time":1.287427401,"remaining_time":4.56451533},
{"learn":[1.043009619],"iteration":220,"passed_time":1.293044089,"remaining_time":4.557834141},
{"learn":[1.042200261],"iteration":221,"passed_time":1.298761038,"remaining_time":4.55151391},
{"learn":[1.041679219],"iteration":222,"passed_time":1.304487777,"remaining_time":4.545233197},
{"learn":[1.040946271],"iteration":223,"passed_time":1.309926919,"remaining_time":4.537961112},
{"learn":[1.040034861],"iteration":224,"passed_time":1.315279139,"remaining_time":4.530405922},
{"learn":[1.03964771],"iteration":225,"passed_time":1.320494198,"remaining_time":4.522400484},
{"learn":[1.038674384],"iteration":226,"passed_time":1.326010419,"remaining_time":4.515445171},
{"learn":[1.037977142],"iteration":227,"passed_time":1.331579322,"remaining_time":4.508680861},
{"learn":[1.037251093],"iteration":228,"passed_time":1.33729075,"remaining_time":4.502406848},
{"learn":[1.036545708],"iteration":229,"passed_time":1.343079533,"remaining_time":4.496396697},
{"learn":[1.035732405],"iteration":230,"passed_time":1.348798338,"remaining_time":4.490155507},
{"learn":[1.034468581],"iteration":231,"passed_time":1.354334099,"remaining_time":4.483312879},
{"learn":[1.033159012],"iteration":232,"passed_time":1.360984171,"remaining_time":4.480149609},
{"learn":[1.032698566],"iteration":233,"passed_time":1.366638593,"remaining_time":4.473697274},
{"learn":[1.031967112],"iteration":234,"passed_time":1.372428856,"remaining_time":4.467693936},
{"learn":[1.031267774],"iteration":235,"passed_time":1.378766032,"remaining_time":4.463462917},
{"learn":[1.030863013],"iteration":236,"passed_time":1.384807755,"remaining_time":4.45826294},
{"learn":[1.030295942],"iteration":237,"passed_time":1.390393899,"remaining_time":4.451597274},
{"learn":[1.029615556],"iteration":238,"passed_time":1.396223917,"remaining_time":4.445717159},
{"learn":[1.028995137],"iteration":239,"passed_time":1.401551031,"remaining_time":4.438244931},
{"learn":[1.02826794],"iteration":240,"passed_time":1.406945856,"remaining_time":4.431003753},
{"learn":[1.027817591],"iteration":241,"passed_time":1.412308211,"remaining_time":4.423676132},
{"learn":[1.026877012],"iteration":242,"passed_time":1.417850357,"remaining_time":4.416924774},
{"learn":[1.026099183],"iteration":243,"passed_time":1.423646241,"remaining_time":4.4109695},
{"learn":[1.025121361],"iteration":244,"passed_time":1.429508049,"remaining_time":4.405218682},
{"learn":[1.024450392],"iteration":245,"passed_time":1.435057128,"remaining_time":4.398508433},
{"learn":[1.023564532],"iteration":246,"passed_time":1.441524265,"remaining_time":4.394606364},
{"learn":[1.022755287],"iteration":247,"passed_time":1.447076012,"remaining_time":4.387907908},
{"learn":[1.022117983],"iteration":248,"passed_time":1.453291858,"remaining_time":4.383221627},
{"learn":[1.020625112],"iteration":249,"passed_time":1.459235898,"remaining_time":4.377707694},
{"learn":[1.020064605],"iteration":250,"passed_time":1.465111783,"remaining_time":4.371986953},
{"learn":[1.019233411],"iteration":251,"passed_time":1.470742114,"remaining_time":4.365536117},
{"learn":[1.018714639],"iteration":252,"passed_time":1.476444941,"remaining_time":4.359305814},
{"learn":[1.017919053],"iteration":253,"passed_time":1.482056731,"remaining_time":4.352812288},
{"learn":[1.017138999],"iteration":254,"passed_time":1.487374754,"remaining_time":4.345467417},
{"learn":[1.016522788],"iteration":255,"passed_time":1.493077293,"remaining_time":4.339255882},
{"learn":[1.015528583],"iteration":256,"passed_time":1.499103315,"remaining_time":4.333983514},
{"learn":[1.015107756],"iteration":257,"passed_time":1.504430377,"remaining_time":4.326695114},
{"learn":[1.014566855],"iteration":258,"passed_time":1.510092492,"remaining_time":4.320380451},
{"learn":[1.013716049],"iteration":259,"passed_time":1.515734271,"remaining_time":4.314012925},
{"learn":[1.013031528],"iteration":260,"passed_time":1.521258277,"remaining_time":4.307317496},
{"learn":[1.012168485],"iteration":261,"passed_time":1.527022341,"remaining_time":4.301307204},
{"learn":[1.011770802],"iteration":262,"passed_time":1.533199898,"remaining_time":4.296457508},
{"learn":[1.010887871],"iteration":263,"passed_time":1.538743615,"remaining_time":4.289830686},
{"learn":[1.01011993],"iteration":264,"passed_time":1.544429807,"remaining_time":4.2836072},
{"learn":[1.009302946],"iteration":265,"passed_time":1.549890849,"remaining_time":4.276766478},
{"learn":[1.008644536],"iteration":266,"passed_time":1.555186582,"remaining_time":4.269482264},
{"learn":[1.007904769],"iteration":267,"passed_time":1.560986839,"remaining_time":4.263590919},
{"learn":[1.007304348],"iteration":268,"passed_time":1.566814857,"remaining_time":4.257775689},
{"learn":[1.00650502],"iteration":269,"passed_time":1.572431352,"remaining_time":4.251388469},
{"learn":[1.005625258],"iteration":270,"passed_time":1.578387459,"remaining_time":4.245920508},
{"learn":[1.004954565],"iteration":271,"passed_time":1.583779082,"remaining_time":4.238938131},
{"learn":[1.004228493],"iteration":272,"passed_time":1.589327093,"remaining_time":4.232383871},
{"learn":[1.003742336],"iteration":273,"passed_time":1.594857117,"remaining_time":4.225789296},
{"learn":[1.002533368],"iteration":274,"passed_time":1.600643358,"remaining_time":4.219877943},
{"learn":[1.001596932],"iteration":275,"passed_time":1.606452333,"remaining_time":4.214027134},
{"learn":[1.000925302],"iteration":276,"passed_time":1.611877593,"remaining_time":4.207175088},
{"learn":[1.000377762],"iteration":277,"passed_time":1.617431699,"remaining_time":4.200667939},
{"learn":[0.9997159351],"iteration":278,"passed_time":1.622748592,"remaining_time":4.193554605},
{"learn":[0.9991832081],"iteration":279,"passed_time":1.628765101,"remaining_time":4.188253118},
{"learn":[0.9987001335],"iteration":280,"passed_time":1.634509134,"remaining_time":4.18224935},
{"learn":[0.9980861634],"iteration":281,"passed_time":1.640135951,"remaining_time":4.175948982},
{"learn":[0.9971484411],"iteration":282,"passed_time":1.646145268,"remaining_time":4.170622464},
{"learn":[0.9962936124],"iteration":283,"passed_time":1.652248587,"remaining_time":4.165528127},
{"learn":[0.9952248058],"iteration":284,"passed_time":1.658240004,"remaining_time":4.160145976},
{"learn":[0.994360969],"iteration":285,"passed_time":1.664434624,"remaining_time":4.155266859},
{"learn":[0.9934866396],"iteration":286,"passed_time":1.670445381,"remaining_time":4.149921799},
{"learn":[0.9927143399],"iteration":287,"passed_time":1.676969777,"remaining_time":4.14584195},
{"learn":[0.9919720037],"iteration":288,"passed_time":1.682906393,"remaining_time":4.14029912},
{"learn":[0.9913770255],"iteration":289,"passed_time":1.688683863,"remaining_time":4.13436394},
{"learn":[0.9906522351],"iteration":290,"passed_time":1.694462424,"remaining_time":4.128432503},
{"learn":[0.990052699],"iteration":291,"passed_time":1.700135615,"remaining_time":4.122246628},
{"learn":[0.9893966016],"iteration":292,"passed_time":1.705709362,"remaining_time":4.115824297},
{"learn":[0.9883321164],"iteration":293,"passed_time":1.711362654,"remaining_time":4.109598753},
{"learn":[0.9875135908],"iteration":294,"passed_time":1.71724548,"remaining_time":4.103925638},
{"learn":[0.9864823793],"iteration":295,"passed_time":1.722849952,"remaining_time":4.097589074},
{"learn":[0.9857925977],"iteration":296,"passed_time":1.728323165,"remaining_time":4.09094675},
{"learn":[0.9848787955],"iteration":297,"passed_time":1.734260858,"remaining_time":4.085406452},
{"learn":[0.9837813218],"iteration":298,"passed_time":1.739998084,"remaining_time":4.079393501},
{"learn":[0.9834842065],"iteration":299,"passed_time":1.746212758,"remaining_time":4.074496434},
{"learn":[0.9826129473],"iteration":300,"passed_time":1.752423532,"remaining_time":4.069581559},
{"learn":[0.9815885979],"iteration":301,"passed_time":1.758486402,"remaining_time":4.064316254},
{"learn":[0.9812031835],"iteration":302,"passed_time":1.764417584,"remaining_time":4.058742759},
{"learn":[0.9807100425],"iteration":303,"passed_time":1.770242705,"remaining_time":4.052924088},
{"learn":[0.9798365679],"iteration":304,"passed_time":1.776449976,"remaining_time":4.047976176},
{"learn":[0.9792587748],"iteration":305,"passed_time":1.782469694,"remaining_time":4.042594665},
{"learn":[0.9786074445],"iteration":306,"passed_time":1.788305343,"remaining_time":4.036793494},
{"learn":[0.9778353525],"iteration":307,"passed_time":1.794220288,"remaining_time":4.031170257},
{"learn":[0.9769083863],"iteration":308,"passed_time":1.799856387,"remaining_time":4.024921563},
{"learn":[0.9752571888],"iteration":309,"passed_time":1.80522878,"remaining_time":4.018089866},
{"learn":[0.9745656318],"iteration":310,"passed_time":1.810747409,"remaining_time":4.011591528},
{"learn":[0.974160573],"iteration":311,"passed_time":1.816098825,"remaining_time":4.004730742},
{"learn":[0.973533389],"iteration":312,"passed_time":1.821598035,"remaining_time":3.998203993},
{"learn":[0.9728115736],"iteration":313,"passed_time":1.827053005,"remaining_time":3.991587138},
{"learn":[0.9720362562],"iteration":314,"passed_time":1.832724404,"remaining_time":3.985448308},
{"learn":[0.9715212815],"iteration":315,"passed_time":1.838140805,"remaining_time":3.978760477},
{"learn":[0.9704857504],"iteration":316,"passed_time":1.844003939,"remaining_time":3.973043188},
{"learn":[0.9696791614],"iteration":317,"passed_time":1.849780439,"remaining_time":3.96713918},
{"learn":[0.9690693329],"iteration":318,"passed_time":1.855997108,"remaining_time":3.962175644},
{"learn":[0.9686696108],"iteration":319,"passed_time":1.86185153,"remaining_time":3.956434502},
{"learn":[0.9680848026],"iteration":320,"passed_time":1.867803068,"remaining_time":3.950898078},
{"learn":[0.9669445095],"iteration":321,"passed_time":1.873801984,"remaining_time":3.945458835},
{"learn":[0.9663687571],"iteration":322,"passed_time":1.879635681,"remaining_time":3.939669833},
{"learn":[0.9652670567],"iteration":323,"passed_time":1.885339656,"remaining_time":3.9336099},
{"learn":[0.9645033933],"iteration":324,"passed_time":1.890883393,"remaining_time":3.927219355},
{"learn":[0.9636507635],"iteration":325,"passed_time":1.896908668,"remaining_time":3.921829577},
{"learn":[0.9630770228],"iteration":326,"passed_time":1.902673748,"remaining_time":3.915900404},
{"learn":[0.9622445848],"iteration":327,"passed_time":1.908389209,"remaining_time":3.909870574},
{"learn":[0.961392894],"iteration":328,"passed_time":1.913928127,"remaining_time":3.903482593},
{"learn":[0.9604992097],"iteration":329,"passed_time":1.919646225,"remaining_time":3.897463548},
{"learn":[0.959630561],"iteration":330,"passed_time":1.925002794,"remaining_time":3.890715618},
{"learn":[0.9589189938],"iteration":331,"passed_time":1.930628681,"remaining_time":3.884517949},
{"learn":[0.9580945265],"iteration":332,"passed_time":1.936563182,"remaining_time":3.878941869},
{"learn":[0.9572162733],"iteration":333,"passed_time":1.942270888,"remaining_time":3.872911411},
{"learn":[0.9567944767],"iteration":334,"passed_time":1.947878829,"remaining_time":3.866684839},
{"learn":[0.9562040334],"iteration":335,"passed_time":1.953497614,"remaining_time":3.860483381},
{"learn":[0.9553994295],"iteration":336,"passed_time":1.959072274,"remaining_time":3.854198569},
{"learn":[0.954218643],"iteration":337,"passed_time":1.965051818,"remaining_time":3.848710957},
{"learn":[0.9535779826],"iteration":338,"passed_time":1.970357322,"remaining_time":3.841906165},
{"learn":[0.9528094153],"iteration":339,"passed_time":1.97626963,"remaining_time":3.836288105},
{"learn":[0.9518128578],"iteration":340,"passed_time":1.982466555,"remaining_time":3.831218356},
{"learn":[0.9508266201],"iteration":341,"passed_time":1.988275958,"remaining_time":3.825396434},
{"learn":[0.9504458895],"iteration":342,"passed_time":1.994376274,"remaining_time":3.820131814},
{"learn":[0.9495138306],"iteration":343,"passed_time":1.999948498,"remaining_time":3.813855274},
{"learn":[0.9484506519],"iteration":344,"passed_time":2.005509077,"remaining_time":3.807560711},
{"learn":[0.9477583334],"iteration":345,"passed_time":2.010955968,"remaining_time":3.801055501},
{"learn":[0.9472054038],"iteration":346,"passed_time":2.016420463,"remaining_time":3.794589518},
{"learn":[0.9465391958],"iteration":347,"passed_time":2.022425258,"remaining_time":3.789141576},
{"learn":[0.9461222574],"iteration":348,"passed_time":2.028076795,"remaining_time":3.7830315},
{"learn":[0.945409575],"iteration":349,"passed_time":2.033744232,"remaining_time":3.776953574},
{"learn":[0.9448521938],"iteration":350,"passed_time":2.0393972,"remaining_time":3.770851233},
{"learn":[0.9438592076],"iteration":351,"passed_time":2.044795337,"remaining_time":3.764282325},
{"learn":[0.9434152509],"iteration":352,"passed_time":2.050467055,"remaining_time":3.758221486},
{"learn":[0.9428490531],"iteration":353,"passed_time":2.056746423,"remaining_time":3.753271721},
{"learn":[0.9416873183],"iteration":354,"passed_time":2.062663067,"remaining_time":3.747655432},
{"learn":[0.9407473356],"iteration":355,"passed_time":2.068599899,"remaining_time":3.742073975},
{"learn":[0.9403102636],"iteration":356,"passed_time":2.074296137,"remaining_time":3.736057188},
{"learn":[0.9398424214],"iteration":357,"passed_time":2.080210388,"remaining_time":3.730433154},
{"learn":[0.9395302835],"iteration":358,"passed_time":2.085963673,"remaining_time":3.724520096},
{"learn":[0.9389129832],"iteration":359,"passed_time":2.091790086,"remaining_time":3.718737931},
{"learn":[0.9381254609],"iteration":360,"passed_time":2.097804978,"remaining_time":3.713289144},
{"learn":[0.9369661255],"iteration":361,"passed_time":2.103358507,"remaining_time":3.70702411},
{"learn":[0.9363417451],"iteration":362,"passed_time":2.109419777,"remaining_time":3.701653988},
{"learn":[0.9355004411],"iteration":363,"passed_time":2.114774963,"remaining_time":3.695046363},
{"learn":[0.9349338485],"iteration":364,"passed_time":2.12021541,"remaining_time":3.688593933},
{"learn":[0.9345618395],"iteration":365,"passed_time":2.125523845,"remaining_time":3.681918354},
{"learn":[0.9339316884],"iteration":366,"passed_time":2.13136088,"remaining_time":3.676161954},
{"learn":[0.9333145447],"iteration":367,"passed_time":2.136928023,"remaining_time":3.669941604},
{"learn":[0.9323776491],"iteration":368,"passed_time":2.142588387,"remaining_time":3.663884207},
{"learn":[0.93165617],"iteration":369,"passed_time":2.147960288,"remaining_time":3.657337788},
{"learn":[0.9310714338],"iteration":370,"passed_time":2.153945471,"remaining_time":3.65183747},
{"learn":[0.9301318009],"iteration":371,"passed_time":2.159509325,"remaining_time":3.64562327},
{"learn":[0.9297929423],"iteration":372,"passed_time":2.164899639,"remaining_time":3.63912084},
{"learn":[0.9291794136],"iteration":373,"passed_time":2.170503791,"remaining_time":3.63298228},
{"learn":[0.9285817023],"iteration":374,"passed_time":2.176035865,"remaining_time":3.626726441},
{"learn":[0.9276826266],"iteration":375,"passed_time":2.181737595,"remaining_time":3.620756009},
{"learn":[0.9270727589],"iteration":376,"passed_time":2.187442606,"remaining_time":3.614792423},
{"learn":[0.9265533695],"iteration":377,"passed_time":2.193066912,"remaining_time":3.608697406},
{"learn":[0.9261969247],"iteration":378,"passed_time":2.19918901,"remaining_time":3.603420515},
{"learn":[0.9251411903],"iteration":379,"passed_time":2.204637342,"remaining_time":3.597039875},
{"learn":[0.9245230669],"iteration":380,"passed_time":2.210699201,"remaining_time":3.591660906},
{"learn":[0.9239208608],"iteration":381,"passed_time":2.216434906,"remaining_time":3.585750711},
{"learn":[0.9234987886],"iteration":382,"passed_time":2.221986216,"remaining_time":3.579544375},
{"learn":[0.9225446193],"iteration":383,"passed_time":2.227842013,"remaining_time":3.573829896},
{"learn":[0.9220496503],"iteration":384,"passed_time":2.233324649,"remaining_time":3.567518594},
{"learn":[0.9215710021],"iteration":385,"passed_time":2.239222727,"remaining_time":3.561872421},
{"learn":[0.9208096495],"iteration":386,"passed_time":2.2453219,"remaining_time":3.556543474},
{"learn":[0.9203864527],"iteration":387,"passed_time":2.250795778,"remaining_time":3.550224269},
{"learn":[0.9198904778],"iteration":388,"passed_time":2.25616798,"remaining_time":3.543749707},
{"learn":[0.9191328091],"iteration":389,"passed_time":2.26171852,"remaining_time":3.537559736},
{"learn":[0.9183373865],"iteration":390,"passed_time":2.267521641,"remaining_time":3.531766443},
{"learn":[0.9174096717],"iteration":391,"passed_time":2.273133227,"remaining_time":3.525676025},
{"learn":[0.9163159313],"iteration":392,"passed_time":2.279300312,"remaining_time":3.520446029},
{"learn":[0.9157619378],"iteration":393,"passed_time":2.285621946,"remaining_time":3.515448983},
{"learn":[0.9151025225],"iteration":394,"passed_time":2.291549948,"remaining_time":3.509842326},
{"learn":[0.9145368315],"iteration":395,"passed_time":2.297448734,"remaining_time":3.504189483},
{"learn":[0.9135569668],"iteration":396,"passed_time":2.303319553,"remaining_time":3.498492923},
{"learn":[0.9129795358],"iteration":397,"passed_time":2.308862656,"remaining_time":3.492299796},
{"learn":[0.9122470378],"iteration":398,"passed_time":2.314851303,"remaining_time":3.486781035},
{"learn":[0.9115327483],"iteration":399,"passed_time":2.32095419,"remaining_time":3.481431285},
{"learn":[0.9107678291],"iteration":400,"passed_time":2.326831122,"remaining_time":3.475740254},
{"learn":[0.9101710283],"iteration":401,"passed_time":2.33237999,"remaining_time":3.469560284},
{"learn":[0.9093805718],"iteration":402,"passed_time":2.338313239,"remaining_time":3.463952863},
{"learn":[0.9086973842],"iteration":403,"passed_time":2.34451666,"remaining_time":3.4587424},
{"learn":[0.9080431234],"iteration":404,"passed_time":2.350616258,"remaining_time":3.453374502},
{"learn":[0.9077753023],"iteration":405,"passed_time":2.356329759,"remaining_time":3.44743812},
{"learn":[0.9072463643],"iteration":406,"passed_time":2.362485164,"remaining_time":3.442146689},
{"learn":[0.906549577],"iteration":407,"passed_time":2.368415204,"remaining_time":3.436524021},
{"learn":[0.9060269997],"iteration":408,"passed_time":2.374195892,"remaining_time":3.430684039},
{"learn":[0.9049418636],"iteration":409,"passed_time":2.380211728,"remaining_time":3.42518273},
{"learn":[0.9045174461],"iteration":410,"passed_time":2.385568758,"remaining_time":3.41873479},
{"learn":[0.904094201],"iteration":411,"passed_time":2.391538535,"remaining_time":3.413166647},
{"learn":[0.9034284834],"iteration":412,"passed_time":2.397295929,"remaining_time":3.407294698},
{"learn":[0.9028123827],"iteration":413,"passed_time":2.402977021,"remaining_time":3.401315301},
{"learn":[0.9020708695],"iteration":414,"passed_time":2.408453243,"remaining_time":3.395048547},
{"learn":[0.9012975996],"iteration":415,"passed_time":2.413865054,"remaining_time":3.388695172},
{"learn":[0.9006097684],"iteration":416,"passed_time":2.419595827,"remaining_time":3.382792248},
{"learn":[0.8994427113],"iteration":417,"passed_time":2.425374459,"remaining_time":3.376956783},
{"learn":[0.8988187195],"iteration":418,"passed_time":2.430961039,"remaining_time":3.370855283},
{"learn":[0.8982398545],"iteration":419,"passed_time":2.43652617,"remaining_time":3.364726615},
{"learn":[0.8975175735],"iteration":420,"passed_time":2.442074503,"remaining_time":3.358577523},
{"learn":[0.897128988],"iteration":421,"passed_time":2.448012042,"remaining_time":3.352964361},
{"learn":[0.8965653778],"iteration":422,"passed_time":2.453729461,"remaining_time":3.347049407},
{"learn":[0.8962596175],"iteration":423,"passed_time":2.459720784,"remaining_time":3.34150748},
{"learn":[0.8954414193],"iteration":424,"passed_time":2.465705501,"remaining_time":3.335954501},
{"learn":[0.8950870759],"iteration":425,"passed_time":2.472106865,"remaining_time":3.330960893},
{"learn":[0.8945503445],"iteration":426,"passed_time":2.477969378,"remaining_time":3.325237597},
{"learn":[0.8942649874],"iteration":427,"passed_time":2.483995901,"remaining_time":3.31973284},
{"learn":[0.8936099843],"iteration":428,"passed_time":2.489596029,"remaining_time":3.313658117},
{"learn":[0.8930960832],"iteration":429,"passed_time":2.495206278,"remaining_time":3.30759902},
{"learn":[0.8924898053],"iteration":430,"passed_time":2.501203065,"remaining_time":3.302052306},
{"learn":[0.8916447829],"iteration":431,"passed_time":2.507028573,"remaining_time":3.296278309},
{"learn":[0.8911004998],"iteration":432,"passed_time":2.512618899,"remaining_time":3.29019611},
{"learn":[0.8902053405],"iteration":433,"passed_time":2.5182434,"remaining_time":3.284160748},
{"learn":[0.8895360601],"iteration":434,"passed_time":2.523706498,"remaining_time":3.277917635},
{"learn":[0.8887830949],"iteration":435,"passed_time":2.52916293,"remaining_time":3.271669478},
{"learn":[0.8880258807],"iteration":436,"passed_time":2.535392428,"remaining_time":3.266420908},
{"learn":[0.8874052218],"iteration":437,"passed_time":2.541076126,"remaining_time":3.260467541},
{"learn":[0.8869833325],"iteration":438,"passed_time":2.546575528,"remaining_time":3.254279889},
{"learn":[0.8864958107],"iteration":439,"passed_time":2.552240116,"remaining_time":3.248305602},
{"learn":[0.8858415502],"iteration":440,"passed_time":2.557660286,"remaining_time":3.242022902},
{"learn":[0.8852135375],"iteration":441,"passed_time":2.563314043,"remaining_time":3.236038995},
{"learn":[0.8845563919],"iteration":442,"passed_time":2.568927669,"remaining_time":3.230006122},
{"learn":[0.8840215597],"iteration":443,"passed_time":2.575054271,"remaining_time":3.224617511},
{"learn":[0.8836523657],"iteration":444,"passed_time":2.580841347,"remaining_time":3.21880213},
{"learn":[0.8831189237],"iteration":445,"passed_time":2.586846553,"remaining_time":3.213257826},
{"learn":[0.8818365455],"iteration":446,"passed_time":2.59290337,"remaining_time":3.20777531},
{"learn":[0.8813948711],"iteration":447,"passed_time":2.599188678,"remaining_time":3.202571764},
{"learn":[0.8806692333],"iteration":448,"passed_time":2.605149732,"remaining_time":3.196965484},
{"learn":[0.8799483792],"iteration":449,"passed_time":2.610874918,"remaining_time":3.191069344},
{"learn":[0.8793934324],"iteration":450,"passed_time":2.616640164,"remaining_time":3.185222727},
{"learn":[0.878764574],"iteration":451,"passed_time":2.622404374,"remaining_time":3.179375215},
{"learn":[0.8779265587],"iteration":452,"passed_time":2.628042395,"remaining_time":3.173375695},
{"learn":[0.8772569025],"iteration":453,"passed_time":2.63376595,"remaining_time":3.167480636},
{"learn":[0.876625016],"iteration":454,"passed_time":2.63957644,"remaining_time":3.161690461},
{"learn":[0.876047349],"iteration":455,"passed_time":2.645414984,"remaining_time":3.155933665},
{"learn":[0.8753397209],"iteration":456,"passed_time":2.651314303,"remaining_time":3.150248723},
{"learn":[0.8748680896],"iteration":457,"passed_time":2.656716628,"remaining_time":3.1439747},
{"learn":[0.8742710164],"iteration":458,"passed_time":2.662672168,"remaining_time":3.13835652},
{"learn":[0.8738669093],"iteration":459,"passed_time":2.668537614,"remaining_time":3.132631112},
{"learn":[0.8731261778],"iteration":460,"passed_time":2.674685577,"remaining_time":3.127235415},
{"learn":[0.8725357116],"iteration":461,"passed_time":2.68076771,"remaining_time":3.121759801},
{"learn":[0.8715116272],"iteration":462,"passed_time":2.686692151,"remaining_time":3.116098671},
{"learn":[0.8709251806],"iteration":463,"passed_time":2.692812103,"remaining_time":3.110662257},
{"learn":[0.8704043688],"iteration":464,"passed_time":2.699265745,"remaining_time":3.105606825},
{"learn":[0.8698358693],"iteration":465,"passed_time":2.70546996,"remaining_time":3.100259568},
{"learn":[0.8692975626],"iteration":466,"passed_time":2.711120966,"remaining_time":3.094277249},
{"learn":[0.8687028194],"iteration":467,"passed_time":2.716422873,"remaining_time":3.087899506},
{"learn":[0.8676830289],"iteration":468,"passed_time":2.721878872,"remaining_time":3.081700812},
{"learn":[0.8671622713],"iteration":469,"passed_time":2.727537332,"remaining_time":3.075733588},
{"learn":[0.8666373864],"iteration":470,"passed_time":2.733333819,"remaining_time":3.069922697},
{"learn":[0.8662697849],"iteration":471,"passed_time":2.738917354,"remaining_time":3.06387365},
{"learn":[0.8654628907],"iteration":472,"passed_time":2.744993817,"remaining_time":3.058375775},
{"learn":[0.8649200944],"iteration":473,"passed_time":2.750840923,"remaining_time":3.05262094},
{"learn":[0.8642534712],"iteration":474,"passed_time":2.756289788,"remaining_time":3.046425555},
{"learn":[0.8631479817],"iteration":475,"passed_time":2.762288218,"remaining_time":3.04083829},
{"learn":[0.8624790415],"iteration":476,"passed_time":2.767919493,"remaining_time":3.03484674},
{"learn":[0.8616786236],"iteration":477,"passed_time":2.773799477,"remaining_time":3.0291283},
{"learn":[0.8609349758],"iteration":478,"passed_time":2.779655136,"remaining_time":3.023382726},
{"learn":[0.8604249036],"iteration":479,"passed_time":2.785533125,"remaining_time":3.017660886},
{"learn":[0.8593628577],"iteration":480,"passed_time":2.791389337,"remaining_time":3.011914898},
{"learn":[0.858836244],"iteration":481,"passed_time":2.797014849,"remaining_time":3.005920522},
{"learn":[0.8583158305],"iteration":482,"passed_time":2.803153953,"remaining_time":3.00047742},
{"learn":[0.8577682056],"iteration":483,"passed_time":2.809000601,"remaining_time":2.994719649},
{"learn":[0.8572938034],"iteration":484,"passed_time":2.814628069,"remaining_time":2.988728774},
{"learn":[0.8565461955],"iteration":485,"passed_time":2.820024799,"remaining_time":2.982495363},
{"learn":[0.8557091127],"iteration":486,"passed_time":2.825472318,"remaining_time":2.97631889},
{"learn":[0.8552046288],"iteration":487,"passed_time":2.831188005,"remaining_time":2.970426759},
{"learn":[0.8543362771],"iteration":488,"passed_time":2.836904044,"remaining_time":2.964535719},
{"learn":[0.8535014249],"iteration":489,"passed_time":2.84254786,"remaining_time":2.958570222},
{"learn":[0.852980011],"iteration":490,"passed_time":2.848309259,"remaining_time":2.952727928},
{"learn":[0.8524763611],"iteration":491,"passed_time":2.854425461,"remaining_time":2.947252305},
{"learn":[0.8521235647],"iteration":492,"passed_time":2.860247824,"remaining_time":2.9414719},
{"learn":[0.851762638],"iteration":493,"passed_time":2.866038816,"remaining_time":2.935659192},
{"learn":[0.8509681572],"iteration":494,"passed_time":2.871448588,"remaining_time":2.92945765},
{"learn":[0.8503423177],"iteration":495,"passed_time":2.87712117,"remaining_time":2.92352635},
{"learn":[0.8496834068],"iteration":496,"passed_time":2.883037409,"remaining_time":2.91784269},
{"learn":[0.8489904686],"iteration":497,"passed_time":2.888715263,"remaining_time":2.911917796},
{"learn":[0.8484714084],"iteration":498,"passed_time":2.894838997,"remaining_time":2.906441558},
{"learn":[0.8482599888],"iteration":499,"passed_time":2.900457358,"remaining_time":2.900457358},
{"learn":[0.8477760682],"iteration":500,"passed_time":2.906208127,"remaining_time":2.894606497},
{"learn":[0.8471312837],"iteration":501,"passed_time":2.911774744,"remaining_time":2.888573351},
{"learn":[0.8463958124],"iteration":502,"passed_time":2.917346898,"remaining_time":2.882547531},
{"learn":[0.8460546264],"iteration":503,"passed_time":2.922761863,"remaining_time":2.876368817},
{"learn":[0.8451537525],"iteration":504,"passed_time":2.928061181,"remaining_time":2.870079772},
{"learn":[0.8447403358],"iteration":505,"passed_time":2.933217645,"remaining_time":2.863655171},
{"learn":[0.8440492465],"iteration":506,"passed_time":2.938614194,"remaining_time":2.857469029},
{"learn":[0.8434074205],"iteration":507,"passed_time":2.944097869,"remaining_time":2.851370377},
{"learn":[0.8431802653],"iteration":508,"passed_time":2.949954551,"remaining_time":2.845633958},
{"learn":[0.8428341093],"iteration":509,"passed_time":2.955910909,"remaining_time":2.839992834},
{"learn":[0.8424258755],"iteration":510,"passed_time":2.961602312,"remaining_time":2.834096929},
{"learn":[0.8415911506],"iteration":511,"passed_time":2.967605747,"remaining_time":2.828499228},
{"learn":[0.8409505025],"iteration":512,"passed_time":2.97327385,"remaining_time":2.822581608},
{"learn":[0.8404449811],"iteration":513,"passed_time":2.978774472,"remaining_time":2.816506602},
{"learn":[0.8397565558],"iteration":514,"passed_time":2.98443977,"remaining_time":2.810588909},
{"learn":[0.8389355235],"iteration":515,"passed_time":2.990690317,"remaining_time":2.80522115},
{"learn":[0.8383518062],"iteration":516,"passed_time":2.996744977,"remaining_time":2.799666971},
{"learn":[0.8374314496],"iteration":517,"passed_time":3.002525769,"remaining_time":2.793856025},
{"learn":[0.8369559108],"iteration":518,"passed_time":3.008329035,"remaining_time":2.788066023},
{"learn":[0.8366794298],"iteration":519,"passed_time":3.014328772,"remaining_time":2.782457328},
{"learn":[0.836289885],"iteration":520,"passed_time":3.019789218,"remaining_time":2.776351316},
{"learn":[0.8357194616],"iteration":521,"passed_time":3.025141021,"remaining_time":2.770148291},
{"learn":[0.8351373095],"iteration":522,"passed_time":3.030529888,"remaining_time":2.763982326},
{"learn":[0.8344610844],"iteration":523,"passed_time":3.035948964,"remaining_time":2.757846769},
{"learn":[0.8336538891],"iteration":524,"passed_time":3.041761705,"remaining_time":2.752070114},
{"learn":[0.8330579517],"iteration":525,"passed_time":3.047401253,"remaining_time":2.746137251},
{"learn":[0.832360563],"iteration":526,"passed_time":3.05264588,"remaining_time":2.739851046},
{"learn":[0.8321234838],"iteration":527,"passed_time":3.058339083,"remaining_time":2.733969786},
{"learn":[0.8315766437],"iteration":528,"passed_time":3.064202332,"remaining_time":2.728240639},
{"learn":[0.8309413187],"iteration":529,"passed_time":3.070160412,"remaining_time":2.722595082},
{"learn":[0.8303914109],"iteration":530,"passed_time":3.076035718,"remaining_time":2.716875239},
{"learn":[0.8297899494],"iteration":531,"passed_time":3.08180832,"remaining_time":2.711064462},
{"learn":[0.8290143309],"iteration":532,"passed_time":3.087657074,"remaining_time":2.705320551},
{"learn":[0.8286684329],"iteration":533,"passed_time":3.093161959,"remaining_time":2.699276167},
{"learn":[0.8277846605],"iteration":534,"passed_time":3.099266949,"remaining_time":2.693755385},
{"learn":[0.8273151132],"iteration":535,"passed_time":3.105492047,"remaining_time":2.688336399},
{"learn":[0.8268804952],"iteration":536,"passed_time":3.111485152,"remaining_time":2.682714386},
{"learn":[0.8264432958],"iteration":537,"passed_time":3.117376785,"remaining_time":2.677003856},
{"learn":[0.8259375443],"iteration":538,"passed_time":3.123280302,"remaining_time":2.671302819},
{"learn":[0.8253872103],"iteration":539,"passed_time":3.129222774,"remaining_time":2.665634215},
{"learn":[0.8247958206],"iteration":540,"passed_time":3.134710049,"remaining_time":2.659578397},
{"learn":[0.8241262666],"iteration":541,"passed_time":3.140544636,"remaining_time":2.653818161},
{"learn":[0.8235945539],"iteration":542,"passed_time":3.146379181,"remaining_time":2.648057616},
{"learn":[0.822953571],"iteration":543,"passed_time":3.152017172,"remaining_time":2.642132041},
{"learn":[0.8222486539],"iteration":544,"passed_time":3.157848273,"remaining_time":2.636368741},
{"learn":[0.8219064758],"iteration":545,"passed_time":3.163356859,"remaining_time":2.630337022},
{"learn":[0.8215454849],"iteration":546,"passed_time":3.169028888,"remaining_time":2.624442571},
{"learn":[0.8207011205],"iteration":547,"passed_time":3.174814749,"remaining_time":2.618642823},
{"learn":[0.8202231032],"iteration":548,"passed_time":3.180339594,"remaining_time":2.612628701},
{"learn":[0.8196474867],"iteration":549,"passed_time":3.18682509,"remaining_time":2.607402347},
{"learn":[0.8190377363],"iteration":550,"passed_time":3.193369312,"remaining_time":2.602219276},
{"learn":[0.8183494345],"iteration":551,"passed_time":3.199213191,"remaining_time":2.596462879},
{"learn":[0.8175142503],"iteration":552,"passed_time":3.205292125,"remaining_time":2.590896166},
{"learn":[0.8167102058],"iteration":553,"passed_time":3.211799396,"remaining_time":2.585672438},
{"learn":[0.8161494094],"iteration":554,"passed_time":3.234956006,"remaining_time":2.593793554},
{"learn":[0.8156136171],"iteration":555,"passed_time":3.2487393,"remaining_time":2.594316995},
{"learn":[0.8148967929],"iteration":556,"passed_time":3.262482672,"remaining_time":2.594757314},
{"learn":[0.8144962186],"iteration":557,"passed_time":3.288531524,"remaining_time":2.604894146},
{"learn":[0.813856446],"iteration":558,"passed_time":3.297497889,"remaining_time":2.60142499},
{"learn":[0.8132740808],"iteration":559,"passed_time":3.304268154,"remaining_time":2.596210693},
{"learn":[0.8127702628],"iteration":560,"passed_time":3.310708773,"remaining_time":2.59073289},
{"learn":[0.8124174543],"iteration":561,"passed_time":3.317849332,"remaining_time":2.585797166},
{"learn":[0.8117817869],"iteration":562,"passed_time":3.326595543,"remaining_time":2.582099915},
{"learn":[0.810810725],"iteration":563,"passed_time":3.334307615,"remaining_time":2.57758532},
{"learn":[0.810190827],"iteration":564,"passed_time":3.341797019,"remaining_time":2.572887971},
{"learn":[0.8096919804],"iteration":565,"passed_time":3.349359019,"remaining_time":2.568236421},
{"learn":[0.8091671068],"iteration":566,"passed_time":3.355961793,"remaining_time":2.562842075},
{"learn":[0.8084567094],"iteration":567,"passed_time":3.362242687,"remaining_time":2.557198663},
{"learn":[0.8080650521],"iteration":568,"passed_time":3.368234601,"remaining_time":2.551334118},
{"learn":[0.8074373359],"iteration":569,"passed_time":3.374303527,"remaining_time":2.545527222},
{"learn":[0.8070876554],"iteration":570,"passed_time":3.380180784,"remaining_time":2.539575405},
{"learn":[0.8065980583],"iteration":571,"passed_time":3.386188845,"remaining_time":2.533721723},
{"learn":[0.8061960376],"iteration":572,"passed_time":3.392055529,"remaining_time":2.527762148},
{"learn":[0.805736023],"iteration":573,"passed_time":3.397626896,"remaining_time":2.521583724},
{"learn":[0.8048684444],"iteration":574,"passed_time":3.403065541,"remaining_time":2.515309313},
{"learn":[0.804456527],"iteration":575,"passed_time":3.408371084,"remaining_time":2.508939825},
{"learn":[0.8040364812],"iteration":576,"passed_time":3.414063518,"remaining_time":2.502857657},
{"learn":[0.8036368876],"iteration":577,"passed_time":3.419290352,"remaining_time":2.4964369},
{"learn":[0.8031694413],"iteration":578,"passed_time":3.42467964,"remaining_time":2.490138391},
{"learn":[0.8024576538],"iteration":579,"passed_time":3.430337707,"remaining_time":2.48403765},
{"learn":[0.8018409678],"iteration":580,"passed_time":3.43556352,"remaining_time":2.477626704},
{"learn":[0.8011596578],"iteration":581,"passed_time":3.440950885,"remaining_time":2.471335859},
{"learn":[0.8003504516],"iteration":582,"passed_time":3.446544711,"remaining_time":2.465195788},
{"learn":[0.7997537584],"iteration":583,"passed_time":3.452487024,"remaining_time":2.459305825},
{"learn":[0.799437819],"iteration":584,"passed_time":3.458207285,"remaining_time":2.453258159},
{"learn":[0.7990101551],"iteration":585,"passed_time":3.463784205,"remaining_time":2.447110343},
{"learn":[0.7983607165],"iteration":586,"passed_time":3.46947211,"remaining_time":2.441042558},
{"learn":[0.7978002995],"iteration":587,"passed_time":3.474968299,"remaining_time":2.434841733},
{"learn":[0.797304157],"iteration":588,"passed_time":3.480858616,"remaining_time":2.428918321},
{"learn":[0.7969992798],"iteration":589,"passed_time":3.486445149,"remaining_time":2.422783917},
{"learn":[0.7964763168],"iteration":590,"passed_time":3.492207276,"remaining_time":2.416772886},
{"learn":[0.7959447635],"iteration":591,"passed_time":3.497910705,"remaining_time":2.410722243},
{"learn":[0.7952767678],"iteration":592,"passed_time":3.503776391,"remaining_time":2.404784133},
{"learn":[0.7946834338],"iteration":593,"passed_time":3.509705806,"remaining_time":2.398889827},
{"learn":[0.7941374675],"iteration":594,"passed_time":3.515362545,"remaining_time":2.392809799},
{"learn":[0.7935785247],"iteration":595,"passed_time":3.520869038,"remaining_time":2.386629348},
{"learn":[0.7932969614],"iteration":596,"passed_time":3.52634553,"remaining_time":2.380430902},
{"learn":[0.7927482503],"iteration":597,"passed_time":3.53198052,"remaining_time":2.37434142},
{"learn":[0.7923655601],"iteration":598,"passed_time":3.537241807,"remaining_time":2.36800328},
{"learn":[0.7919490794],"iteration":599,"passed_time":3.543176724,"remaining_time":2.362117816},
{"learn":[0.7916127502],"iteration":600,"passed_time":3.54892635,"remaining_time":2.356109174},
{"learn":[0.7910889836],"iteration":601,"passed_time":3.55538436,"remaining_time":2.350569726},
{"learn":[0.7903674974],"iteration":602,"passed_time":3.561007487,"remaining_time":2.344477566},
{"learn":[0.7895946479],"iteration":603,"passed_time":3.567123257,"remaining_time":2.33870995},
{"learn":[0.7888716789],"iteration":604,"passed_time":3.572995742,"remaining_time":2.332782344},
{"learn":[0.788369314],"iteration":605,"passed_time":3.578609304,"remaining_time":2.326686577},
{"learn":[0.787826202],"iteration":606,"passed_time":3.584528605,"remaining_time":2.320790349},
{"learn":[0.7873154151],"iteration":607,"passed_time":3.590238851,"remaining_time":2.314759259},
{"learn":[0.7868409914],"iteration":608,"passed_time":3.596015532,"remaining_time":2.308771877},
{"learn":[0.7864137708],"iteration":609,"passed_time":3.60189949,"remaining_time":2.302853772},
{"learn":[0.785925252],"iteration":610,"passed_time":3.607950031,"remaining_time":2.297041836},
{"learn":[0.7854548201],"iteration":611,"passed_time":3.613956362,"remaining_time":2.291201092},
{"learn":[0.7845781786],"iteration":612,"passed_time":3.619648009,"remaining_time":2.285161141},
{"learn":[0.7841571643],"iteration":613,"passed_time":3.625173609,"remaining_time":2.279017936},
{"learn":[0.7838650328],"iteration":614,"passed_time":3.630637762,"remaining_time":2.272838274},
{"learn":[0.783444617],"iteration":615,"passed_time":3.636152687,"remaining_time":2.266692584},
{"learn":[0.7827322244],"iteration":616,"passed_time":3.642076885,"remaining_time":2.260802994},
{"learn":[0.7818475069],"iteration":617,"passed_time":3.648192605,"remaining_time":2.255031675},
{"learn":[0.7813858367],"iteration":618,"passed_time":3.653946018,"remaining_time":2.24903624},
{"learn":[0.7810196424],"iteration":619,"passed_time":3.659600935,"remaining_time":2.242981218},
{"learn":[0.780574044],"iteration":620,"passed_time":3.666143426,"remaining_time":2.237469176},
{"learn":[0.7801827723],"iteration":621,"passed_time":3.672438833,"remaining_time":2.231803664},
{"learn":[0.7798016205],"iteration":622,"passed_time":3.678188131,"remaining_time":2.225805659},
{"learn":[0.7793393957],"iteration":623,"passed_time":3.684127974,"remaining_time":2.219923266},
{"learn":[0.7788279851],"iteration":624,"passed_time":3.689727912,"remaining_time":2.213836747},
{"learn":[0.7783567572],"iteration":625,"passed_time":3.695851151,"remaining_time":2.208064426},
{"learn":[0.777994435],"iteration":626,"passed_time":3.701394667,"remaining_time":2.20194611},
{"learn":[0.7775947865],"iteration":627,"passed_time":3.707156789,"remaining_time":2.195959117},
{"learn":[0.7768734606],"iteration":628,"passed_time":3.713017651,"remaining_time":2.190031079},
{"learn":[0.775912093],"iteration":629,"passed_time":3.718537253,"remaining_time":2.183902831},
{"learn":[0.7753213221],"iteration":630,"passed_time":3.723951316,"remaining_time":2.177714795},
{"learn":[0.7751401237],"iteration":631,"passed_time":3.729127622,"remaining_time":2.171390767},
{"learn":[0.7746634278],"iteration":632,"passed_time":3.73457107,"remaining_time":2.165225249},
{"learn":[0.7742502727],"iteration":633,"passed_time":3.740536181,"remaining_time":2.159363158},
{"learn":[0.7737099105],"iteration":634,"passed_time":3.746420321,"remaining_time":2.1534542},
{"learn":[0.7732686263],"iteration":635,"passed_time":3.752117828,"remaining_time":2.147438505},
{"learn":[0.7730240231],"iteration":636,"passed_time":3.757651624,"remaining_time":2.141330517},
{"learn":[0.7721189015],"iteration":637,"passed_time":3.764112946,"remaining_time":2.135750606},
{"learn":[0.7717914249],"iteration":638,"passed_time":3.770237968,"remaining_time":2.129977944},
{"learn":[0.7714561425],"iteration":639,"passed_time":3.775832612,"remaining_time":2.123905844},
{"learn":[0.7709766201],"iteration":640,"passed_time":3.782334038,"remaining_time":2.118343088},
{"learn":[0.7705578811],"iteration":641,"passed_time":3.788746629,"remaining_time":2.112727871},
{"learn":[0.7702028694],"iteration":642,"passed_time":3.794669962,"remaining_time":2.106838533},
{"learn":[0.7696599478],"iteration":643,"passed_time":3.80082759,"remaining_time":2.101078606},
{"learn":[0.7691833499],"iteration":644,"passed_time":3.806586633,"remaining_time":2.09509807},
{"learn":[0.7688314832],"iteration":645,"passed_time":3.812274405,"remaining_time":2.089079163},
{"learn":[0.7682293574],"iteration":646,"passed_time":3.817581695,"remaining_time":2.082853692},
{"learn":[0.7677900797],"iteration":647,"passed_time":3.823159939,"remaining_time":2.076778239},
{"learn":[0.7673246497],"iteration":648,"passed_time":3.828473107,"remaining_time":2.070560956},
{"learn":[0.7667557165],"iteration":649,"passed_time":3.833954814,"remaining_time":2.064437208},
{"learn":[0.7660619241],"iteration":650,"passed_time":3.839342834,"remaining_time":2.058265206},
{"learn":[0.7656606157],"iteration":651,"passed_time":3.844862973,"remaining_time":2.052166127},
{"learn":[0.7651388964],"iteration":652,"passed_time":3.850458171,"remaining_time":2.046108707},
{"learn":[0.7643895249],"iteration":653,"passed_time":3.85615746,"remaining_time":2.040107769},
{"learn":[0.7639429737],"iteration":654,"passed_time":3.861961816,"remaining_time":2.034163094},
{"learn":[0.7638506743],"iteration":655,"passed_time":3.867558838,"remaining_time":2.028110123},
{"learn":[0.7635791514],"iteration":656,"passed_time":3.873380876,"remaining_time":2.022176013},
{"learn":[0.7632233726],"iteration":657,"passed_time":3.879430841,"remaining_time":2.016360711},
{"learn":[0.7627006616],"iteration":658,"passed_time":3.885319586,"remaining_time":2.010461273},
{"learn":[0.762222664],"iteration":659,"passed_time":3.891859031,"remaining_time":2.004897077},
{"learn":[0.761913605],"iteration":660,"passed_time":3.897879989,"remaining_time":1.999064018},
{"learn":[0.7614321891],"iteration":661,"passed_time":3.903720465,"remaining_time":1.993138243},
{"learn":[0.7608840557],"iteration":662,"passed_time":3.909365029,"remaining_time":1.987113144},
{"learn":[0.7605625871],"iteration":663,"passed_time":3.915467435,"remaining_time":1.981320871},
{"learn":[0.7600536748],"iteration":664,"passed_time":3.921745082,"remaining_time":1.975615944},
{"learn":[0.7595573721],"iteration":665,"passed_time":3.927590121,"remaining_time":1.969692343},
{"learn":[0.7591282935],"iteration":666,"passed_time":3.93312548,"remaining_time":1.96361437},
{"learn":[0.7585683012],"iteration":667,"passed_time":3.93905163,"remaining_time":1.957732247},
{"learn":[0.7580403465],"iteration":668,"passed_time":3.944583586,"remaining_time":1.951654958},
{"learn":[0.7576447905],"iteration":669,"passed_time":3.949959262,"remaining_time":1.945502323},
{"learn":[0.7573219241],"iteration":670,"passed_time":3.955294814,"remaining_time":1.93933233},
{"learn":[0.7567517008],"iteration":671,"passed_time":3.960761471,"remaining_time":1.933228813},
{"learn":[0.75647895],"iteration":672,"passed_time":3.966512282,"remaining_time":1.927265254},
{"learn":[0.7561425251],"iteration":673,"passed_time":3.972018081,"remaining_time":1.92118382},
{"learn":[0.7555877637],"iteration":674,"passed_time":3.977545249,"remaining_time":1.915114379},
{"learn":[0.7553256984],"iteration":675,"passed_time":3.983226034,"remaining_time":1.90912017},
{"learn":[0.7548393784],"iteration":676,"passed_time":3.989344673,"remaining_time":1.903335789},
{"learn":[0.7539256143],"iteration":677,"passed_time":3.995226691,"remaining_time":1.897438045},
{"learn":[0.7531165647],"iteration":678,"passed_time":4.000923058,"remaining_time":1.89145258},
{"learn":[0.752750812],"iteration":679,"passed_time":4.006627742,"remaining_time":1.885471878},
{"learn":[0.7522332565],"iteration":680,"passed_time":4.012021062,"remaining_time":1.879346136},
{"learn":[0.7516256253],"iteration":681,"passed_time":4.017644635,"remaining_time":1.873329903},
{"learn":[0.7512281929],"iteration":682,"passed_time":4.02336382,"remaining_time":1.867359196},
{"learn":[0.7505970451],"iteration":683,"passed_time":4.028917981,"remaining_time":1.861312985},
{"learn":[0.750049611],"iteration":684,"passed_time":4.033917264,"remaining_time":1.855013049},
{"learn":[0.7495698133],"iteration":685,"passed_time":4.039686361,"remaining_time":1.849069267},
{"learn":[0.7492209608],"iteration":686,"passed_time":4.045329979,"remaining_time":1.843068826},
{"learn":[0.7488419824],"iteration":687,"passed_time":4.050405477,"remaining_time":1.836811786},
{"learn":[0.7484881565],"iteration":688,"passed_time":4.05623325,"remaining_time":1.830897737},
{"learn":[0.7480252801],"iteration":689,"passed_time":4.061669529,"remaining_time":1.824808049},
{"learn":[0.7474127148],"iteration":690,"passed_time":4.067287414,"remaining_time":1.818801463},
{"learn":[0.7470844404],"iteration":691,"passed_time":4.072701882,"remaining_time":1.812705462},
{"learn":[0.7466258449],"iteration":692,"passed_time":4.078623395,"remaining_time":1.806836049},
{"learn":[0.7457059889],"iteration":693,"passed_time":4.084444735,"remaining_time":1.800922319},
{"learn":[0.7451356665],"iteration":694,"passed_time":4.090580211,"remaining_time":1.795146711},
{"learn":[0.7446735323],"iteration":695,"passed_time":4.096726739,"remaining_time":1.789374897},
{"learn":[0.7441104525],"iteration":696,"passed_time":4.103134157,"remaining_time":1.783715422},
{"learn":[0.7437949381],"iteration":697,"passed_time":4.108823437,"remaining_time":1.777743092},
{"learn":[0.74298507],"iteration":698,"passed_time":4.114563084,"remaining_time":1.771793259},
{"learn":[0.7422449741],"iteration":699,"passed_time":4.120239963,"remaining_time":1.765817127},
{"learn":[0.7419436985],"iteration":700,"passed_time":4.125674241,"remaining_time":1.759738371},
{"learn":[0.7413082997],"iteration":701,"passed_time":4.131254786,"remaining_time":1.753723542},
{"learn":[0.7409116838],"iteration":702,"passed_time":4.136911616,"remaining_time":1.747742176},
{"learn":[0.7403522565],"iteration":703,"passed_time":4.142780567,"remaining_time":1.74185092},
{"learn":[0.740073227],"iteration":704,"passed_time":4.148262004,"remaining_time":1.735797576},
{"learn":[0.739610149],"iteration":705,"passed_time":4.154334375,"remaining_time":1.729991935},
{"learn":[0.7392639078],"iteration":706,"passed_time":4.160538901,"remaining_time":1.724240308},
{"learn":[0.7387738091],"iteration":707,"passed_time":4.166318764,"remaining_time":1.718312259},
{"learn":[0.7382284751],"iteration":708,"passed_time":4.172058651,"remaining_time":1.712368219},
{"learn":[0.7379015911],"iteration":709,"passed_time":4.177850554,"remaining_time":1.706446001},
{"learn":[0.7374454343],"iteration":710,"passed_time":4.183894959,"remaining_time":1.700626783},
{"learn":[0.7371633955],"iteration":711,"passed_time":4.189620766,"remaining_time":1.694678063},
{"learn":[0.736806144],"iteration":712,"passed_time":4.195380114,"remaining_time":1.688743468},
{"learn":[0.7363418782],"iteration":713,"passed_time":4.201137146,"remaining_time":1.682808437},
{"learn":[0.7358494887],"iteration":714,"passed_time":4.206686383,"remaining_time":1.676791076},
{"learn":[0.7354981937],"iteration":715,"passed_time":4.212646245,"remaining_time":1.670937896},
{"learn":[0.7349935625],"iteration":716,"passed_time":4.218422067,"remaining_time":1.665011778},
{"learn":[0.7343252264],"iteration":717,"passed_time":4.224216883,"remaining_time":1.659093539},
{"learn":[0.7338288153],"iteration":718,"passed_time":4.229925703,"remaining_time":1.653142034},
{"learn":[0.7334091628],"iteration":719,"passed_time":4.235450741,"remaining_time":1.647119732},
{"learn":[0.7330472607],"iteration":720,"passed_time":4.240951287,"remaining_time":1.641089333},
{"learn":[0.7327321587],"iteration":721,"passed_time":4.246896018,"remaining_time":1.635231431},
{"learn":[0.732350159],"iteration":722,"passed_time":4.253252541,"remaining_time":1.629531056},
{"learn":[0.7320356392],"iteration":723,"passed_time":4.259571197,"remaining_time":1.623814434},
{"learn":[0.731638124],"iteration":724,"passed_time":4.265549029,"remaining_time":1.617966873},
{"learn":[0.731068533],"iteration":725,"passed_time":4.271884368,"remaining_time":1.61225388},
{"learn":[0.730797208],"iteration":726,"passed_time":4.277877771,"remaining_time":1.606410772},
{"learn":[0.7302812671],"iteration":727,"passed_time":4.284374682,"remaining_time":1.600755376},
{"learn":[0.7299156056],"iteration":728,"passed_time":4.290457175,"remaining_time":1.594943614},
{"learn":[0.7292296409],"iteration":729,"passed_time":4.296435688,"remaining_time":1.589092652},
{"learn":[0.728747126],"iteration":730,"passed_time":4.302323298,"remaining_time":1.583207889},
{"learn":[0.7283931009],"iteration":731,"passed_time":4.308016378,"remaining_time":1.577251898},
{"learn":[0.7279967463],"iteration":732,"passed_time":4.313599687,"remaining_time":1.571256639},
{"learn":[0.7273808821],"iteration":733,"passed_time":4.319337944,"remaining_time":1.565318655},
{"learn":[0.7271360153],"iteration":734,"passed_time":4.32521185,"remaining_time":1.559430123},
{"learn":[0.7267393797],"iteration":735,"passed_time":4.330660448,"remaining_time":1.553389074},
{"learn":[0.7262179782],"iteration":736,"passed_time":4.336287993,"remaining_time":1.54741349},
{"learn":[0.7258510506],"iteration":737,"passed_time":4.341820034,"remaining_time":1.541404944},
{"learn":[0.7255887981],"iteration":738,"passed_time":4.347283455,"remaining_time":1.535373453},
{"learn":[0.725093388],"iteration":739,"passed_time":4.353188014,"remaining_time":1.529498492},
{"learn":[0.7249065647],"iteration":740,"passed_time":4.358822887,"remaining_time":1.523529187},
{"learn":[0.7246450576],"iteration":741,"passed_time":4.364706844,"remaining_time":1.517647393},
{"learn":[0.724230703],"iteration":742,"passed_time":4.370653356,"remaining_time":1.511787231},
{"learn":[0.7238358701],"iteration":743,"passed_time":4.376446005,"remaining_time":1.505873894},
{"learn":[0.72347872],"iteration":744,"passed_time":4.381961925,"remaining_time":1.499866162},
{"learn":[0.7229991417],"iteration":745,"passed_time":4.387662439,"remaining_time":1.4939226},
{"learn":[0.7225940615],"iteration":746,"passed_time":4.393644759,"remaining_time":1.488075133},
{"learn":[0.7221914202],"iteration":747,"passed_time":4.399783977,"remaining_time":1.482280163},
{"learn":[0.7217123398],"iteration":748,"passed_time":4.405748678,"remaining_time":1.476425792},
{"learn":[0.721329559],"iteration":749,"passed_time":4.411472852,"remaining_time":1.470490951},
{"learn":[0.7208712578],"iteration":750,"passed_time":4.417309275,"remaining_time":1.464593887},
{"learn":[0.7204122437],"iteration":751,"passed_time":4.422890474,"remaining_time":1.458612816},
{"learn":[0.7200298144],"iteration":752,"passed_time":4.428318911,"remaining_time":1.452582697},
{"learn":[0.7195496923],"iteration":753,"passed_time":4.43393627,"remaining_time":1.446615812},
{"learn":[0.7191937358],"iteration":754,"passed_time":4.439975423,"remaining_time":1.440786727},
{"learn":[0.7187542344],"iteration":755,"passed_time":4.445542536,"remaining_time":1.434804734},
{"learn":[0.7182560029],"iteration":756,"passed_time":4.450860362,"remaining_time":1.428743815},
{"learn":[0.7179412975],"iteration":757,"passed_time":4.456478137,"remaining_time":1.422780619},
{"learn":[0.7176636695],"iteration":758,"passed_time":4.462526196,"remaining_time":1.416954958},
{"learn":[0.7171286812],"iteration":759,"passed_time":4.468115086,"remaining_time":1.410983711},
{"learn":[0.7165707222],"iteration":760,"passed_time":4.47694352,"remaining_time":1.406030882},
{"learn":[0.716116429],"iteration":761,"passed_time":4.483097998,"remaining_time":1.400232708},
{"learn":[0.7157571181],"iteration":762,"passed_time":4.489086441,"remaining_time":1.394382027},
{"learn":[0.7155689129],"iteration":763,"passed_time":4.494727478,"remaining_time":1.388423671},
{"learn":[0.7151203755],"iteration":764,"passed_time":4.500862738,"remaining_time":1.382617965},
{"learn":[0.7147497585],"iteration":765,"passed_time":4.506565021,"remaining_time":1.376679132},
{"learn":[0.7141116963],"iteration":766,"passed_time":4.512089706,"remaining_time":1.370686964},
{"learn":[0.7136560972],"iteration":767,"passed_time":4.517799948,"remaining_time":1.364752068},
{"learn":[0.7130628178],"iteration":768,"passed_time":4.523313704,"remaining_time":1.358758733},
{"learn":[0.71271179],"iteration":769,"passed_time":4.528845935,"remaining_time":1.352772163},
{"learn":[0.7123226994],"iteration":770,"passed_time":4.534533161,"remaining_time":1.346832807},
{"learn":[0.7121007772],"iteration":771,"passed_time":4.540058562,"remaining_time":1.340846311},
{"learn":[0.7114410619],"iteration":772,"passed_time":4.545534961,"remaining_time":1.334846619},
{"learn":[0.7110222272],"iteration":773,"passed_time":4.550879235,"remaining_time":1.328809699},
{"learn":[0.7103838206],"iteration":774,"passed_time":4.556375641,"remaining_time":1.322818734},
{"learn":[0.7099980081],"iteration":775,"passed_time":4.561963569,"remaining_time":1.316855463},
{"learn":[0.70953038],"iteration":776,"passed_time":4.567988753,"remaining_time":1.311018651},
{"learn":[0.7089794008],"iteration":777,"passed_time":4.574365654,"remaining_time":1.305281716},
{"learn":[0.7085956153],"iteration":778,"passed_time":4.580473979,"remaining_time":1.299466944},
{"learn":[0.7080093278],"iteration":779,"passed_time":4.586716174,"remaining_time":1.293689177},
{"learn":[0.7075943369],"iteration":780,"passed_time":4.592369546,"remaining_time":1.28774511},
{"learn":[0.7073812384],"iteration":781,"passed_time":4.597985505,"remaining_time":1.281791356},
{"learn":[0.7069572323],"iteration":782,"passed_time":4.603365948,"remaining_time":1.275773194},
{"learn":[0.7067261894],"iteration":783,"passed_time":4.609151801,"remaining_time":1.269868353},
{"learn":[0.7063011466],"iteration":784,"passed_time":4.614569165,"remaining_time":1.263862892},
{"learn":[0.7059982689],"iteration":785,"passed_time":4.620176355,"remaining_time":1.257910611},
{"learn":[0.7057811185],"iteration":786,"passed_time":4.625757513,"remaining_time":1.25195216},
{"learn":[0.7050748066],"iteration":787,"passed_time":4.631824745,"remaining_time":1.246125439},
{"learn":[0.7045015291],"iteration":788,"passed_time":4.638326002,"remaining_time":1.240414178},
{"learn":[0.704129748],"iteration":789,"passed_time":4.644030419,"remaining_time":1.234489099},
{"learn":[0.703397805],"iteration":790,"passed_time":4.649830411,"remaining_time":1.22858983},
{"learn":[0.7030411986],"iteration":791,"passed_time":4.655413396,"remaining_time":1.222633821},
{"learn":[0.7027298261],"iteration":792,"passed_time":4.661362263,"remaining_time":1.21677426},
{"learn":[0.7024176499],"iteration":793,"passed_time":4.667337147,"remaining_time":1.210921224},
{"learn":[0.701824651],"iteration":794,"passed_time":4.673379217,"remaining_time":1.205085207},
{"learn":[0.7014045726],"iteration":795,"passed_time":4.67954108,"remaining_time":1.199279372},
{"learn":[0.7010151639],"iteration":796,"passed_time":4.68542205,"remaining_time":1.193401099},
{"learn":[0.7003656904],"iteration":797,"passed_time":4.691259971,"remaining_time":1.187511922},
{"learn":[0.6999993815],"iteration":798,"passed_time":4.69682455,"remaining_time":1.181554111},
{"learn":[0.6994096377],"iteration":799,"passed_time":4.7024155,"remaining_time":1.175603875},
{"learn":[0.6988556533],"iteration":800,"passed_time":4.708343657,"remaining_time":1.169738312},
{"learn":[0.6984086868],"iteration":801,"passed_time":4.714304459,"remaining_time":1.163880652},
{"learn":[0.6982365827],"iteration":802,"passed_time":4.719948925,"remaining_time":1.157945129},
{"learn":[0.6978433781],"iteration":803,"passed_time":4.725590357,"remaining_time":1.15200959},
{"learn":[0.6974945006],"iteration":804,"passed_time":4.731208911,"remaining_time":1.146069239},
{"learn":[0.6969192123],"iteration":805,"passed_time":4.736921724,"remaining_time":1.140152375},
{"learn":[0.6965458582],"iteration":806,"passed_time":4.742801799,"remaining_time":1.134276019},
{"learn":[0.6959151212],"iteration":807,"passed_time":4.748456518,"remaining_time":1.128346103},
{"learn":[0.695600352],"iteration":808,"passed_time":4.754132589,"remaining_time":1.122421909},
{"learn":[0.6952401832],"iteration":809,"passed_time":4.759793079,"remaining_time":1.116494673},
{"learn":[0.6947883804],"iteration":810,"passed_time":4.765826159,"remaining_time":1.110654925},
{"learn":[0.6939904948],"iteration":811,"passed_time":4.771704775,"remaining_time":1.104778938},
{"learn":[0.6937302914],"iteration":812,"passed_time":4.777708374,"remaining_time":1.098931692},
{"learn":[0.6933372993],"iteration":813,"passed_time":4.783740707,"remaining_time":1.093090628},
{"learn":[0.6929057327],"iteration":814,"passed_time":4.789831179,"remaining_time":1.087262292},
{"learn":[0.6927037213],"iteration":815,"passed_time":4.795178928,"remaining_time":1.081265837},
{"learn":[0.6925206079],"iteration":816,"passed_time":4.800655792,"remaining_time":1.07529989},
{"learn":[0.6918250683],"iteration":817,"passed_time":4.806095955,"remaining_time":1.069326973},
{"learn":[0.6914081437],"iteration":818,"passed_time":4.811665827,"remaining_time":1.063384023},
{"learn":[0.6907889242],"iteration":819,"passed_time":4.817436308,"remaining_time":1.057486019},
{"learn":[0.6902908642],"iteration":820,"passed_time":4.823217526,"remaining_time":1.051590666},
{"learn":[0.689680025],"iteration":821,"passed_time":4.829609496,"remaining_time":1.045827847},
{"learn":[0.6889782923],"iteration":822,"passed_time":4.835226034,"remaining_time":1.039896729},
{"learn":[0.6885916901],"iteration":823,"passed_time":4.840975757,"remaining_time":1.033994822},
{"learn":[0.6878835244],"iteration":824,"passed_time":4.846465621,"remaining_time":1.028038162},
{"learn":[0.6872892995],"iteration":825,"passed_time":4.851864226,"remaining_time":1.022063408},
{"learn":[0.6869371674],"iteration":826,"passed_time":4.85724401,"remaining_time":1.016086111},
{"learn":[0.6864794847],"iteration":827,"passed_time":4.863094303,"remaining_time":1.010207995},
{"learn":[0.6860405187],"iteration":828,"passed_time":4.869038751,"remaining_time":1.004349368},
{"learn":[0.6856982915],"iteration":829,"passed_time":4.874873194,"remaining_time":0.9984680037},
{"learn":[0.6855062021],"iteration":830,"passed_time":4.880621201,"remaining_time":0.9925691733},
{"learn":[0.685139731],"iteration":831,"passed_time":4.886263554,"remaining_time":0.9866493714},
{"learn":[0.6843190782],"iteration":832,"passed_time":4.892148933,"remaining_time":0.9807789577},
{"learn":[0.6837138741],"iteration":833,"passed_time":4.897949903,"remaining_time":0.9748917072},
{"learn":[0.6833907746],"iteration":834,"passed_time":4.903911076,"remaining_time":0.9690363204},
{"learn":[0.6828696141],"iteration":835,"passed_time":4.90997225,"remaining_time":0.9632002979},
{"learn":[0.6824516533],"iteration":836,"passed_time":4.915803906,"remaining_time":0.9573190403},
{"learn":[0.6820747597],"iteration":837,"passed_time":4.92200485,"remaining_time":0.9515092907},
{"learn":[0.6817649077],"iteration":838,"passed_time":4.927641312,"remaining_time":0.9455902875},
{"learn":[0.6813337047],"iteration":839,"passed_time":4.93295906,"remaining_time":0.9396112495},
{"learn":[0.6808727755],"iteration":840,"passed_time":4.938624602,"remaining_time":0.9336995383},
{"learn":[0.6803120402],"iteration":841,"passed_time":4.944189207,"remaining_time":0.9277694711},
{"learn":[0.6797278846],"iteration":842,"passed_time":4.9496379,"remaining_time":0.9218186837},
{"learn":[0.6791054027],"iteration":843,"passed_time":4.955027731,"remaining_time":0.9158582061},
{"learn":[0.6787753844],"iteration":844,"passed_time":4.960412304,"remaining_time":0.909898115},
{"learn":[0.6784971966],"iteration":845,"passed_time":4.965914452,"remaining_time":0.9039607868},
{"learn":[0.6779241943],"iteration":846,"passed_time":4.972193681,"remaining_time":0.8981648561},
{"learn":[0.6776483139],"iteration":847,"passed_time":4.977786087,"remaining_time":0.8922446759},
{"learn":[0.6772966857],"iteration":848,"passed_time":4.983562566,"remaining_time":0.8863580064},
{"learn":[0.6768111274],"iteration":849,"passed_time":4.989754806,"remaining_time":0.8805449657},
{"learn":[0.6764797381],"iteration":850,"passed_time":4.995544229,"remaining_time":0.8746605053},
{"learn":[0.6761399284],"iteration":851,"passed_time":5.001187142,"remaining_time":0.8687508181},
{"learn":[0.6757843966],"iteration":852,"passed_time":5.007323015,"remaining_time":0.8629267094},
{"learn":[0.6755758759],"iteration":853,"passed_time":5.013021647,"remaining_time":0.8570271199},
{"learn":[0.6752904033],"iteration":854,"passed_time":5.018832358,"remaining_time":0.851147008},
{"learn":[0.6746601969],"iteration":855,"passed_time":5.025116487,"remaining_time":0.8453466987},
{"learn":[0.6741619482],"iteration":856,"passed_time":5.030950075,"remaining_time":0.8394700826},
{"learn":[0.6737631562],"iteration":857,"passed_time":5.036412517,"remaining_time":0.8335321416},
{"learn":[0.6734299328],"iteration":858,"passed_time":5.041749398,"remaining_time":0.8275746975},
{"learn":[0.6731122434],"iteration":859,"passed_time":5.047151805,"remaining_time":0.8216293636},
{"learn":[0.67275441],"iteration":860,"passed_time":5.052415278,"remaining_time":0.8156628613},
{"learn":[0.6723481151],"iteration":861,"passed_time":5.058013542,"remaining_time":0.8097515879},
{"learn":[0.6718691944],"iteration":862,"passed_time":5.063918195,"remaining_time":0.8038896787},
{"learn":[0.6715267689],"iteration":863,"passed_time":5.069525988,"remaining_time":0.7979809425},
{"learn":[0.6710921436],"iteration":864,"passed_time":5.075004873,"remaining_time":0.7920527837},
{"learn":[0.6708304454],"iteration":865,"passed_time":5.080856245,"remaining_time":0.7861832989},
{"learn":[0.6705399205],"iteration":866,"passed_time":5.086419197,"remaining_time":0.7802696116},
{"learn":[0.6700464229],"iteration":867,"passed_time":5.092068658,"remaining_time":0.7743698881},
{"learn":[0.6696160777],"iteration":868,"passed_time":5.097655875,"remaining_time":0.7684613574},
{"learn":[0.6692880691],"iteration":869,"passed_time":5.103369936,"remaining_time":0.7625725191},
{"learn":[0.6689262146],"iteration":870,"passed_time":5.109550553,"remaining_time":0.7567531817},
{"learn":[0.6686322758],"iteration":871,"passed_time":5.115478473,"remaining_time":0.7508959226},
{"learn":[0.6682439961],"iteration":872,"passed_time":5.121116809,"remaining_time":0.7449963743},
{"learn":[0.6679076569],"iteration":873,"passed_time":5.127427793,"remaining_time":0.7391943957},
{"learn":[0.6671445508],"iteration":874,"passed_time":5.13363504,"remaining_time":0.7333764342},
{"learn":[0.6665846],"iteration":875,"passed_time":5.139807389,"remaining_time":0.727552644},
{"learn":[0.6662456907],"iteration":876,"passed_time":5.145866705,"remaining_time":0.721712206},
{"learn":[0.6659565873],"iteration":877,"passed_time":5.15169268,"remaining_time":0.7158388462},
{"learn":[0.6656793027],"iteration":878,"passed_time":5.157324619,"remaining_time":0.7099388838},
{"learn":[0.6653877321],"iteration":879,"passed_time":5.163285715,"remaining_time":0.7040844157},
{"learn":[0.6648748548],"iteration":880,"passed_time":5.169066901,"remaining_time":0.6982054043},
{"learn":[0.6643896779],"iteration":881,"passed_time":5.17479715,"remaining_time":0.6923198001},
{"learn":[0.6637382644],"iteration":882,"passed_time":5.180583191,"remaining_time":0.6864419403},
{"learn":[0.6634138986],"iteration":883,"passed_time":5.186171218,"remaining_time":0.6805383046},
{"learn":[0.6628284992],"iteration":884,"passed_time":5.192332389,"remaining_time":0.6747098585},
{"learn":[0.6624702876],"iteration":885,"passed_time":5.198186198,"remaining_time":0.6688411135},
{"learn":[0.6619788831],"iteration":886,"passed_time":5.204008248,"remaining_time":0.6629683563},
{"learn":[0.6615084386],"iteration":887,"passed_time":5.209670571,"remaining_time":0.6570755675},
{"learn":[0.6612257324],"iteration":888,"passed_time":5.21507077,"remaining_time":0.6511505686},
{"learn":[0.6606862805],"iteration":889,"passed_time":5.220930957,"remaining_time":0.6452836015},
{"learn":[0.6603154877],"iteration":890,"passed_time":5.226861511,"remaining_time":0.6394252577},
{"learn":[0.6596042451],"iteration":891,"passed_time":5.233240602,"remaining_time":0.6336210594},
{"learn":[0.6592367541],"iteration":892,"passed_time":5.238778749,"remaining_time":0.6277148109},
{"learn":[0.658746471],"iteration":893,"passed_time":5.244424354,"remaining_time":0.621822127},
{"learn":[0.6580416523],"iteration":894,"passed_time":5.249861552,"remaining_time":0.6159055452},
{"learn":[0.6576701085],"iteration":895,"passed_time":5.255544328,"remaining_time":0.6100185381},
{"learn":[0.6572816955],"iteration":896,"passed_time":5.261151453,"remaining_time":0.6041232995},
{"learn":[0.6569382511],"iteration":897,"passed_time":5.267048711,"remaining_time":0.5982616576},
{"learn":[0.656653358],"iteration":898,"passed_time":5.272937923,"remaining_time":0.5923990326},
{"learn":[0.6563212115],"iteration":899,"passed_time":5.279101183,"remaining_time":0.5865667981},
{"learn":[0.6559873674],"iteration":900,"passed_time":5.284734054,"remaining_time":0.5806755509},
{"learn":[0.6555482555],"iteration":901,"passed_time":5.290702632,"remaining_time":0.5748213502},
{"learn":[0.6551212341],"iteration":902,"passed_time":5.29639877,"remaining_time":0.5689376309},
{"learn":[0.6548092002],"iteration":903,"passed_time":5.301885654,"remaining_time":0.5630321049},
{"learn":[0.6544090288],"iteration":904,"passed_time":5.307507427,"remaining_time":0.5571416636},
{"learn":[0.6538679106],"iteration":905,"passed_time":5.313185586,"remaining_time":0.5512576657},
{"learn":[0.6536050896],"iteration":906,"passed_time":5.319004793,"remaining_time":0.5453885841},
{"learn":[0.6533310479],"iteration":907,"passed_time":5.324932957,"remaining_time":0.539530652},
{"learn":[0.652911941],"iteration":908,"passed_time":5.330760906,"remaining_time":0.5336625329},
{"learn":[0.6524594701],"iteration":909,"passed_time":5.337053691,"remaining_time":0.5278404749},
{"learn":[0.6521102346],"iteration":910,"passed_time":5.342894089,"remaining_time":0.5219731877},
{"learn":[0.6517076007],"iteration":911,"passed_time":5.348696233,"remaining_time":0.5161022681},
{"learn":[0.6513078364],"iteration":912,"passed_time":5.353867817,"remaining_time":0.5101714131},
{"learn":[0.6508880249],"iteration":913,"passed_time":5.35930454,"remaining_time":0.5042671667},
{"learn":[0.6505162418],"iteration":914,"passed_time":5.365099236,"remaining_time":0.4983971968},
{"learn":[0.6499659046],"iteration":915,"passed_time":5.371247139,"remaining_time":0.4925597813},
{"learn":[0.6497084751],"iteration":916,"passed_time":5.376939167,"remaining_time":0.4866804263},
{"learn":[0.6491065291],"iteration":917,"passed_time":5.382571375,"remaining_time":0.4807961359},
{"learn":[0.6487409107],"iteration":918,"passed_time":5.388055746,"remaining_time":0.4748993639},
{"learn":[0.6484605665],"iteration":919,"passed_time":5.393803187,"remaining_time":0.469026364},
{"learn":[0.6480322418],"iteration":920,"passed_time":5.399679135,"remaining_time":0.4631646598},
{"learn":[0.6476591706],"iteration":921,"passed_time":5.405183497,"remaining_time":0.4572714889},
{"learn":[0.6472256843],"iteration":922,"passed_time":5.411070474,"remaining_time":0.4514110796},
{"learn":[0.6468703482],"iteration":923,"passed_time":5.416676235,"remaining_time":0.4455274825},
{"learn":[0.6467040082],"iteration":924,"passed_time":5.422422534,"remaining_time":0.4396558811},
{"learn":[0.6461691421],"iteration":925,"passed_time":5.428214888,"remaining_time":0.4337882308},
{"learn":[0.6457289154],"iteration":926,"passed_time":5.434023091,"remaining_time":0.427921991},
{"learn":[0.6452411437],"iteration":927,"passed_time":5.43999786,"remaining_time":0.4220687995},
{"learn":[0.6451163603],"iteration":928,"passed_time":5.44592048,"remaining_time":0.4162113607},
{"learn":[0.6448694893],"iteration":929,"passed_time":5.451898303,"remaining_time":0.4103579368},
{"learn":[0.6444237265],"iteration":930,"passed_time":5.457687668,"remaining_time":0.4044902783},
{"learn":[0.6439978991],"iteration":931,"passed_time":5.463267985,"remaining_time":0.3986075354},
{"learn":[0.6434225431],"iteration":932,"passed_time":5.468999008,"remaining_time":0.3927362632},
{"learn":[0.6432420867],"iteration":933,"passed_time":5.474676139,"remaining_time":0.3868614831},
{"learn":[0.6428760817],"iteration":934,"passed_time":5.480165947,"remaining_time":0.3809741033},
{"learn":[0.6425509853],"iteration":935,"passed_time":5.48598862,"remaining_time":0.375110333},
{"learn":[0.6421981188],"iteration":936,"passed_time":5.491817298,"remaining_time":0.3692470542},
{"learn":[0.6418956859],"iteration":937,"passed_time":5.497698255,"remaining_time":0.3633873047},
{"learn":[0.6416403818],"iteration":938,"passed_time":5.50325443,"remaining_time":0.3575064113},
{"learn":[0.6413910565],"iteration":939,"passed_time":5.508758035,"remaining_time":0.3516228533},
{"learn":[0.6410976091],"iteration":940,"passed_time":5.515067728,"remaining_time":0.3457906439},
{"learn":[0.6408405988],"iteration":941,"passed_time":5.520596806,"remaining_time":0.3399093575},
{"learn":[0.6402432005],"iteration":942,"passed_time":5.526768196,"remaining_time":0.3340676428},
{"learn":[0.6397772835],"iteration":943,"passed_time":5.532662542,"remaining_time":0.3282087949},
{"learn":[0.639486855],"iteration":944,"passed_time":5.538391257,"remaining_time":0.3223402319},
{"learn":[0.63897859],"iteration":945,"passed_time":5.54422991,"remaining_time":0.3164782401},
{"learn":[0.6385633231],"iteration":946,"passed_time":5.550432908,"remaining_time":0.3106366886},
{"learn":[0.638337968],"iteration":947,"passed_time":5.556440089,"remaining_time":0.3047836336},
{"learn":[0.6379277505],"iteration":948,"passed_time":5.562055244,"remaining_time":0.2989091859},
{"learn":[0.6376608157],"iteration":949,"passed_time":5.567747345,"remaining_time":0.293039334},
{"learn":[0.6372842856],"iteration":950,"passed_time":5.573351514,"remaining_time":0.2871653251},
{"learn":[0.6369786468],"iteration":951,"passed_time":5.578972597,"remaining_time":0.281292736},
{"learn":[0.6367300428],"iteration":952,"passed_time":5.584790225,"remaining_time":0.2754303679},
{"learn":[0.6362190853],"iteration":953,"passed_time":5.590475753,"remaining_time":0.2695617239},
{"learn":[0.6359440155],"iteration":954,"passed_time":5.59658885,"remaining_time":0.2637136107},
{"learn":[0.6356776584],"iteration":955,"passed_time":5.602840186,"remaining_time":0.2578713056},
{"learn":[0.6353699178],"iteration":956,"passed_time":5.60852729,"remaining_time":0.2520027936},
{"learn":[0.6350331034],"iteration":957,"passed_time":5.614227111,"remaining_time":0.2461352178},
{"learn":[0.6347920202],"iteration":958,"passed_time":5.620471613,"remaining_time":0.2402912786},
{"learn":[0.6345318973],"iteration":959,"passed_time":5.626567857,"remaining_time":0.2344403274},
{"learn":[0.6341085692],"iteration":960,"passed_time":5.632432825,"remaining_time":0.2285794799},
{"learn":[0.633701136],"iteration":961,"passed_time":5.638375372,"remaining_time":0.2227216883},
{"learn":[0.6333504579],"iteration":962,"passed_time":5.644217459,"remaining_time":0.2168598608},
{"learn":[0.6331552179],"iteration":963,"passed_time":5.650073242,"remaining_time":0.2109985858},
{"learn":[0.6327611171],"iteration":964,"passed_time":5.655651093,"remaining_time":0.2051272417},
{"learn":[0.6323474126],"iteration":965,"passed_time":5.661427269,"remaining_time":0.1992634857},
{"learn":[0.6320839018],"iteration":966,"passed_time":5.66704083,"remaining_time":0.1933943613},
{"learn":[0.6317128039],"iteration":967,"passed_time":5.672684308,"remaining_time":0.187526754},
{"learn":[0.631219236],"iteration":968,"passed_time":5.678634012,"remaining_time":0.1816694059},
{"learn":[0.6309880723],"iteration":969,"passed_time":5.684309188,"remaining_time":0.1758033769},
{"learn":[0.6305626305],"iteration":970,"passed_time":5.690527818,"remaining_time":0.1699539719},
{"learn":[0.630223957],"iteration":971,"passed_time":5.696496247,"remaining_time":0.1640965997},
{"learn":[0.6299131112],"iteration":972,"passed_time":5.702590448,"remaining_time":0.1582424893},
{"learn":[0.629539433],"iteration":973,"passed_time":5.708020202,"remaining_time":0.1523701491},
{"learn":[0.6292500741],"iteration":974,"passed_time":5.713895184,"remaining_time":0.1465101329},
{"learn":[0.6288070856],"iteration":975,"passed_time":5.719727809,"remaining_time":0.1406490445},
{"learn":[0.6285082599],"iteration":976,"passed_time":5.725465553,"remaining_time":0.1347857807},
{"learn":[0.6281251574],"iteration":977,"passed_time":5.731622116,"remaining_time":0.1289321948},
{"learn":[0.6276746831],"iteration":978,"passed_time":5.737616164,"remaining_time":0.123074504},
{"learn":[0.6272667252],"iteration":979,"passed_time":5.743393787,"remaining_time":0.1172121181},
{"learn":[0.6269251654],"iteration":980,"passed_time":5.749036091,"remaining_time":0.1113472841},
{"learn":[0.6264372247],"iteration":981,"passed_time":5.754711451,"remaining_time":0.1054835093},
{"learn":[0.6259326677],"iteration":982,"passed_time":5.760373736,"remaining_time":0.09961989167},
{"learn":[0.625707922],"iteration":983,"passed_time":5.766152772,"remaining_time":0.09375858167},
{"learn":[0.6254452408],"iteration":984,"passed_time":5.772013303,"remaining_time":0.08789867974},
{"learn":[0.6251689103],"iteration":985,"passed_time":5.77762348,"remaining_time":0.08203522183},
{"learn":[0.6248706936],"iteration":986,"passed_time":5.783675284,"remaining_time":0.07617809392},
{"learn":[0.6242895569],"iteration":987,"passed_time":5.78964803,"remaining_time":0.07031961171},
{"learn":[0.6237805605],"iteration":988,"passed_time":5.795761037,"remaining_time":0.06446245845},
{"learn":[0.623506011],"iteration":989,"passed_time":5.801443402,"remaining_time":0.05860043841},
{"learn":[0.6232964808],"iteration":990,"passed_time":5.807116654,"remaining_time":0.05273869817},
{"learn":[0.6228734934],"iteration":991,"passed_time":5.813177675,"remaining_time":0.04688046512},
{"learn":[0.6226184616],"iteration":992,"passed_time":5.818939587,"remaining_time":0.04101971511},
{"learn":[0.6221850715],"iteration":993,"passed_time":5.824733162,"remaining_time":0.0351593551},
{"learn":[0.6217831197],"iteration":994,"passed_time":5.830480058,"remaining_time":0.02929889477},
{"learn":[0.6213791731],"iteration":995,"passed_time":5.836135702,"remaining_time":0.02343829599},
{"learn":[0.620965894],"iteration":996,"passed_time":5.841918256,"remaining_time":0.01757849024},
{"learn":[0.6203861475],"iteration":997,"passed_time":5.847857454,"remaining_time":0.01171915322},
{"learn":[0.6199490941],"iteration":998,"passed_time":5.853493221,"remaining_time":0.005859352573},
{"learn":[0.6196783638],"iteration":999,"passed_time":5.859222382,"remaining_time":0}
]}